{"Success":true,"Error":null,"PricedItineraries":[{"IsPassportMandatory":true,"TicketType":"eTicket","DirectionInd":1,"ValidatingAirlineCode":"WY","FareSourceCode":"353337383736263339263232303535","AirItineraryPricingInfo":{"FareType":2,"DivideInPartyIndicator":false,"ItinTotalFare":{"BaseFare":2979000.0,"TotalFare":4418850.0,"TotalCommission":0.0,"TotalTax":1439850.0,"ServiceTax":0.0,"Currency":"IRR"},"PtcFareBreakdown":[{"PassengerFare":{"BaseFare":2979000.0,"TotalFare":4418850.0,"Commission":0.0,"ServiceTax":0.0,"Surcharges":[],"Taxes":[{"Amount":1439850.0,"Currency":"IRR","TaxCode":""}],"Currency":"IRR"},"PassengerTypeQuantity":{"PassengerType":1,"Quantity":1},"FareBasisCodes":["USEOWAE"]}],"FareInfoes":[]},"OriginDestinationOptions":[{"FlightSegments":[{"DepartureDateTime":"2017-03-08T06:15:00","ArrivalDateTime":"2017-03-08T07:30:00","StopQuantity":0,"FlightNumber":"602","ResBookDesigCode":"U","JourneyDuration":"01:15","DepartureAirportLocationCode":"DXB","ArrivalAirportLocationCode":"MCT","MarketingAirlineCode":"WY","MarriageGroup":null,"Eticket":true,"CabinClassCode":1,"MealCode":null,"OperatingAirline":{"Code":"WY","FlightNumber":null,"Equipment":"738"},"SeatsRemaining":{"Number":4,"BelowMinimum":true},"IsCharter":false,"IsReturn":false},{"DepartureDateTime":"2017-03-08T08:50:00","ArrivalDateTime":"2017-03-08T13:40:00","StopQuantity":0,"FlightNumber":"283","ResBookDesigCode":"U","JourneyDuration":"03:20","DepartureAirportLocationCode":"MCT","ArrivalAirportLocationCode":"BLR","MarketingAirlineCode":"WY","MarriageGroup":null,"Eticket":true,"CabinClassCode":1,"MealCode":null,"OperatingAirline":{"Code":"WY","FlightNumber":null,"Equipment":"738"},"SeatsRemaining":{"Number":4,"BelowMinimum":true},"IsCharter":false,"IsReturn":false}]}]},{"IsPassportMandatory":true,"TicketType":"eTicket","DirectionInd":1,"ValidatingAirlineCode":"WY","FareSourceCode":"353337383737263339263232303535","AirItineraryPricingInfo":{"FareType":2,"DivideInPartyIndicator":false,"ItinTotalFare":{"BaseFare":2979000.0,"TotalFare":4418850.0,"TotalCommission":0.0,"TotalTax":1439850.0,"ServiceTax":0.0,"Currency":"IRR"},"PtcFareBreakdown":[{"PassengerFare":{"BaseFare":2979000.0,"TotalFare":4418850.0,"Commission":0.0,"ServiceTax":0.0,"Surcharges":[],"Taxes":[{"Amount":1439850.0,"Currency":"IRR","TaxCode":""}],"Currency":"IRR"},"PassengerTypeQuantity":{"PassengerType":1,"Quantity":1},"FareBasisCodes":["USEOWAE"]}],"FareInfoes":[]},"OriginDestinationOptions":[{"FlightSegments":[{"DepartureDateTime":"2017-03-08T23:15:00","ArrivalDateTime":"2017-03-09T00:30:00","StopQuantity":0,"FlightNumber":"614","ResBookDesigCode":"U","JourneyDuration":"01:15","DepartureAirportLocationCode":"DXB","ArrivalAirportLocationCode":"MCT","MarketingAirlineCode":"WY","MarriageGroup":null,"Eticket":true,"CabinClassCode":1,"MealCode":null,"OperatingAirline":{"Code":"WY","FlightNumber":null,"Equipment":"738"},"SeatsRemaining":{"Number":4,"BelowMinimum":true},"IsCharter":false,"IsReturn":false},{"DepartureDateTime":"2017-03-09T02:45:00","ArrivalDateTime":"2017-03-09T07:35:00","StopQuantity":0,"FlightNumber":"281","ResBookDesigCode":"U","JourneyDuration":"03:20","DepartureAirportLocationCode":"MCT","ArrivalAirportLocationCode":"BLR","MarketingAirlineCode":"WY","MarriageGroup":null,"Eticket":true,"CabinClassCode":1,"MealCode":null,"OperatingAirline":{"Code":"WY","FlightNumber":null,"Equipment":"738"},"SeatsRemaining":{"Number":4,"BelowMinimum":true},"IsCharter":false,"IsReturn":false}]}]},{"IsPassportMandatory":true,"TicketType":"eTicket","DirectionInd":1,"ValidatingAirlineCode":"WY","FareSourceCode":"353337383738263339263232303535","AirItineraryPricingInfo":{"FareType":2,"DivideInPartyIndicator":false,"ItinTotalFare":{"BaseFare":2979000.0,"TotalFare":4418850.0,"TotalCommission":0.0,"TotalTax":1439850.0,"ServiceTax":0.0,"Currency":"IRR"},"PtcFareBreakdown":[{"PassengerFare":{"BaseFare":2979000.0,"TotalFare":4418850.0,"Commission":0.0,"ServiceTax":0.0,"Surcharges":[],"Taxes":[{"Amount":1439850.0,"Currency":"IRR","TaxCode":""}],"Currency":"IRR"},"PassengerTypeQuantity":{"PassengerType":1,"Quantity":1},"FareBasisCodes":["USEOWAE"]}],"FareInfoes":[]},"OriginDestinationOptions":[{"FlightSegments":[{"DepartureDateTime":"2017-03-08T22:45:00","ArrivalDateTime":"2017-03-08T23:55:00","StopQuantity":0,"FlightNumber":"612","ResBookDesigCode":"U","JourneyDuration":"01:10","DepartureAirportLocationCode":"DXB","ArrivalAirportLocationCode":"MCT","MarketingAirlineCode":"WY","MarriageGroup":null,"Eticket":true,"CabinClassCode":1,"MealCode":null,"OperatingAirline":{"Code":"WY","FlightNumber":null,"Equipment":"738"},"SeatsRemaining":{"Number":4,"BelowMinimum":true},"IsCharter":false,"IsReturn":false},{"DepartureDateTime":"2017-03-09T02:45:00","ArrivalDateTime":"2017-03-09T07:35:00","StopQuantity":0,"FlightNumber":"281","ResBookDesigCode":"U","JourneyDuration":"03:20","DepartureAirportLocationCode":"MCT","ArrivalAirportLocationCode":"BLR","MarketingAirlineCode":"WY","MarriageGroup":null,"Eticket":true,"CabinClassCode":1,"MealCode":null,"OperatingAirline":{"Code":"WY","FlightNumber":null,"Equipment":"738"},"SeatsRemaining":{"Number":4,"BelowMinimum":true},"IsCharter":false,"IsReturn":false}]}]},{"IsPassportMandatory":true,"TicketType":"eTicket","DirectionInd":1,"ValidatingAirlineCode":"WY","FareSourceCode":"353337383739263339263232303535","AirItineraryPricingInfo":{"FareType":2,"DivideInPartyIndicator":false,"ItinTotalFare":{"BaseFare":2979000.0,"TotalFare":4418850.0,"TotalCommission":0.0,"TotalTax":1439850.0,"ServiceTax":0.0,"Currency":"IRR"},"PtcFareBreakdown":[{"PassengerFare":{"BaseFare":2979000.0,"TotalFare":4418850.0,"Commission":0.0,"ServiceTax":0.0,"Surcharges":[],"Taxes":[{"Amount":1439850.0,"Currency":"IRR","TaxCode":""}],"Currency":"IRR"},"PassengerTypeQuantity":{"PassengerType":1,"Quantity":1},"FareBasisCodes":["USEOWAE"]}],"FareInfoes":[]},"OriginDestinationOptions":[{"FlightSegments":[{"DepartureDateTime":"2017-03-08T20:40:00","ArrivalDateTime":"2017-03-08T21:55:00","StopQuantity":0,"FlightNumber":"624","ResBookDesigCode":"U","JourneyDuration":"01:15","DepartureAirportLocationCode":"DXB","ArrivalAirportLocationCode":"MCT","MarketingAirlineCode":"WY","MarriageGroup":null,"Eticket":true,"CabinClassCode":1,"MealCode":null,"OperatingAirline":{"Code":"WY","FlightNumber":null,"Equipment":"738"},"SeatsRemaining":{"Number":4,"BelowMinimum":true},"IsCharter":false,"IsReturn":false},{"DepartureDateTime":"2017-03-09T02:45:00","ArrivalDateTime":"2017-03-09T07:35:00","StopQuantity":0,"FlightNumber":"281","ResBookDesigCode":"U","JourneyDuration":"03:20","DepartureAirportLocationCode":"MCT","ArrivalAirportLocationCode":"BLR","MarketingAirlineCode":"WY","MarriageGroup":null,"Eticket":true,"CabinClassCode":1,"MealCode":null,"OperatingAirline":{"Code":"WY","FlightNumber":null,"Equipment":"738"},"SeatsRemaining":{"Number":4,"BelowMinimum":true},"IsCharter":false,"IsReturn":false}]}]},{"IsPassportMandatory":true,"TicketType":"eTicket","DirectionInd":1,"ValidatingAirlineCode":"WY","FareSourceCode":"353337383830263339263232303535","AirItineraryPricingInfo":{"FareType":2,"DivideInPartyIndicator":false,"ItinTotalFare":{"BaseFare":2979000.0,"TotalFare":4418850.0,"TotalCommission":0.0,"TotalTax":1439850.0,"ServiceTax":0.0,"Currency":"IRR"},"PtcFareBreakdown":[{"PassengerFare":{"BaseFare":2979000.0,"TotalFare":4418850.0,"Commission":0.0,"ServiceTax":0.0,"Surcharges":[],"Taxes":[{"Amount":1439850.0,"Currency":"IRR","TaxCode":""}],"Currency":"IRR"},"PassengerTypeQuantity":{"PassengerType":1,"Quantity":1},"FareBasisCodes":["USEOWAE"]}],"FareInfoes":[]},"OriginDestinationOptions":[{"FlightSegments":[{"DepartureDateTime":"2017-03-08T17:15:00","ArrivalDateTime":"2017-03-08T18:30:00","StopQuantity":0,"FlightNumber":"610","ResBookDesigCode":"U","JourneyDuration":"01:15","DepartureAirportLocationCode":"DXB","ArrivalAirportLocationCode":"MCT","MarketingAirlineCode":"WY","MarriageGroup":null,"Eticket":true,"CabinClassCode":1,"MealCode":null,"OperatingAirline":{"Code":"WY","FlightNumber":null,"Equipment":"738"},"SeatsRemaining":{"Number":4,"BelowMinimum":true},"IsCharter":false,"IsReturn":false},{"DepartureDateTime":"2017-03-09T02:45:00","ArrivalDateTime":"2017-03-09T07:35:00","StopQuantity":0,"FlightNumber":"281","ResBookDesigCode":"U","JourneyDuration":"03:20","DepartureAirportLocationCode":"MCT","ArrivalAirportLocationCode":"BLR","MarketingAirlineCode":"WY","MarriageGroup":null,"Eticket":true,"CabinClassCode":1,"MealCode":null,"OperatingAirline":{"Code":"WY","FlightNumber":null,"Equipment":"738"},"SeatsRemaining":{"Number":4,"BelowMinimum":true},"IsCharter":false,"IsReturn":false}]}]},{"IsPassportMandatory":true,"TicketType":"eTicket","DirectionInd":1,"ValidatingAirlineCode":"WY","FareSourceCode":"353337383831263339263232303535","AirItineraryPricingInfo":{"FareType":2,"DivideInPartyIndicator":false,"ItinTotalFare":{"BaseFare":2979000.0,"TotalFare":4418850.0,"TotalCommission":0.0,"TotalTax":1439850.0,"ServiceTax":0.0,"Currency":"IRR"},"PtcFareBreakdown":[{"PassengerFare":{"BaseFare":2979000.0,"TotalFare":4418850.0,"Commission":0.0,"ServiceTax":0.0,"Surcharges":[],"Taxes":[{"Amount":1439850.0,"Currency":"IRR","TaxCode":""}],"Currency":"IRR"},"PassengerTypeQuantity":{"PassengerType":1,"Quantity":1},"FareBasisCodes":["USEOWAE"]}],"FareInfoes":[]},"OriginDestinationOptions":[{"FlightSegments":[{"DepartureDateTime":"2017-03-08T23:15:00","ArrivalDateTime":"2017-03-09T00:30:00","StopQuantity":0,"FlightNumber":"614","ResBookDesigCode":"U","JourneyDuration":"01:15","DepartureAirportLocationCode":"DXB","ArrivalAirportLocationCode":"MCT","MarketingAirlineCode":"WY","MarriageGroup":null,"Eticket":true,"CabinClassCode":1,"MealCode":null,"OperatingAirline":{"Code":"WY","FlightNumber":null,"Equipment":"738"},"SeatsRemaining":{"Number":4,"BelowMinimum":true},"IsCharter":false,"IsReturn":false},{"DepartureDateTime":"2017-03-09T08:50:00","ArrivalDateTime":"2017-03-09T13:40:00","StopQuantity":0,"FlightNumber":"283","ResBookDesigCode":"U","JourneyDuration":"03:20","DepartureAirportLocationCode":"MCT","ArrivalAirportLocationCode":"BLR","MarketingAirlineCode":"WY","MarriageGroup":null,"Eticket":true,"CabinClassCode":1,"MealCode":null,"OperatingAirline":{"Code":"WY","FlightNumber":null,"Equipment":"738"},"SeatsRemaining":{"Number":4,"BelowMinimum":true},"IsCharter":false,"IsReturn":false}]}]},{"IsPassportMandatory":true,"TicketType":"eTicket","DirectionInd":1,"ValidatingAirlineCode":"WY","FareSourceCode":"353337383832263339263232303535","AirItineraryPricingInfo":{"FareType":2,"DivideInPartyIndicator":false,"ItinTotalFare":{"BaseFare":2979000.0,"TotalFare":4418850.0,"TotalCommission":0.0,"TotalTax":1439850.0,"ServiceTax":0.0,"Currency":"IRR"},"PtcFareBreakdown":[{"PassengerFare":{"BaseFare":2979000.0,"TotalFare":4418850.0,"Commission":0.0,"ServiceTax":0.0,"Surcharges":[],"Taxes":[{"Amount":1439850.0,"Currency":"IRR","TaxCode":""}],"Currency":"IRR"},"PassengerTypeQuantity":{"PassengerType":1,"Quantity":1},"FareBasisCodes":["USEOWAE"]}],"FareInfoes":[]},"OriginDestinationOptions":[{"FlightSegments":[{"DepartureDateTime":"2017-03-08T22:45:00","ArrivalDateTime":"2017-03-08T23:55:00","StopQuantity":0,"FlightNumber":"612","ResBookDesigCode":"U","JourneyDuration":"01:10","DepartureAirportLocationCode":"DXB","ArrivalAirportLocationCode":"MCT","MarketingAirlineCode":"WY","MarriageGroup":null,"Eticket":true,"CabinClassCode":1,"MealCode":null,"OperatingAirline":{"Code":"WY","FlightNumber":null,"Equipment":"738"},"SeatsRemaining":{"Number":4,"BelowMinimum":true},"IsCharter":false,"IsReturn":false},{"DepartureDateTime":"2017-03-09T08:50:00","ArrivalDateTime":"2017-03-09T13:40:00","StopQuantity":0,"FlightNumber":"283","ResBookDesigCode":"U","JourneyDuration":"03:20","DepartureAirportLocationCode":"MCT","ArrivalAirportLocationCode":"BLR","MarketingAirlineCode":"WY","MarriageGroup":null,"Eticket":true,"CabinClassCode":1,"MealCode":null,"OperatingAirline":{"Code":"WY","FlightNumber":null,"Equipment":"738"},"SeatsRemaining":{"Number":4,"BelowMinimum":true},"IsCharter":false,"IsReturn":false}]}]},{"IsPassportMandatory":true,"TicketType":"eTicket","DirectionInd":1,"ValidatingAirlineCode":"QR","FareSourceCode":"353337383833263339263232303535","AirItineraryPricingInfo":{"FareType":2,"DivideInPartyIndicator":false,"ItinTotalFare":{"BaseFare":2358375.0,"TotalFare":5138775.0,"TotalCommission":124125.0,"TotalTax":2780400.0,"ServiceTax":0.0,"Currency":"IRR"},"PtcFareBreakdown":[{"PassengerFare":{"BaseFare":2358375.0,"TotalFare":5138775.0,"Commission":124125.0,"ServiceTax":0.0,"Surcharges":[],"Taxes":[{"Amount":2780400.0,"Currency":"IRR","TaxCode":""}],"Currency":"IRR"},"PassengerTypeQuantity":{"PassengerType":1,"Quantity":1},"FareBasisCodes":["OLAEP4NO"]}],"FareInfoes":[]},"OriginDestinationOptions":[{"FlightSegments":[{"DepartureDateTime":"2017-03-08T17:45:00","ArrivalDateTime":"2017-03-08T17:50:00","StopQuantity":0,"FlightNumber":"1031","ResBookDesigCode":"O","JourneyDuration":"01:05","DepartureAirportLocationCode":"DWC","ArrivalAirportLocationCode":"DOH","MarketingAirlineCode":"QR","MarriageGroup":null,"Eticket":true,"CabinClassCode":1,"MealCode":null,"OperatingAirline":{"Code":"QR","FlightNumber":null,"Equipment":"320"},"SeatsRemaining":{"Number":9,"BelowMinimum":true},"IsCharter":false,"IsReturn":false},{"DepartureDateTime":"2017-03-08T20:00:00","ArrivalDateTime":"2017-03-09T02:15:00","StopQuantity":0,"FlightNumber":"572","ResBookDesigCode":"O","JourneyDuration":"03:45","DepartureAirportLocationCode":"DOH","ArrivalAirportLocationCode":"BLR","MarketingAirlineCode":"QR","MarriageGroup":null,"Eticket":true,"CabinClassCode":1,"MealCode":null,"OperatingAirline":{"Code":"QR","FlightNumber":null,"Equipment":"77W"},"SeatsRemaining":{"Number":9,"BelowMinimum":true},"IsCharter":false,"IsReturn":false}]}]},{"IsPassportMandatory":true,"TicketType":"eTicket","DirectionInd":1,"ValidatingAirlineCode":"QR","FareSourceCode":"353337383834263339263232303535","AirItineraryPricingInfo":{"FareType":2,"DivideInPartyIndicator":false,"ItinTotalFare":{"BaseFare":2358375.0,"TotalFare":5486325.0,"TotalCommission":124125.0,"TotalTax":3127950.0,"ServiceTax":0.0,"Currency":"IRR"},"PtcFareBreakdown":[{"PassengerFare":{"BaseFare":2358375.0,"TotalFare":5486325.0,"Commission":124125.0,"ServiceTax":0.0,"Surcharges":[],"Taxes":[{"Amount":3127950.0,"Currency":"IRR","TaxCode":""}],"Currency":"IRR"},"PassengerTypeQuantity":{"PassengerType":1,"Quantity":1},"FareBasisCodes":["OLAEP4NO"]}],"FareInfoes":[]},"OriginDestinationOptions":[{"FlightSegments":[{"DepartureDateTime":"2017-03-08T18:30:00","ArrivalDateTime":"2017-03-08T18:40:00","StopQuantity":0,"FlightNumber":"1013","ResBookDesigCode":"O","JourneyDuration":"01:10","DepartureAirportLocationCode":"DXB","ArrivalAirportLocationCode":"DOH","MarketingAirlineCode":"QR","MarriageGroup":null,"Eticket":true,"CabinClassCode":1,"MealCode":null,"OperatingAirline":{"Code":"QR","FlightNumber":null,"Equipment":"320"},"SeatsRemaining":{"Number":9,"BelowMinimum":true},"IsCharter":false,"IsReturn":false},{"DepartureDateTime":"2017-03-08T20:00:00","ArrivalDateTime":"2017-03-09T02:15:00","StopQuantity":0,"FlightNumber":"572","ResBookDesigCode":"O","JourneyDuration":"03:45","DepartureAirportLocationCode":"DOH","ArrivalAirportLocationCode":"BLR","MarketingAirlineCode":"QR","MarriageGroup":null,"Eticket":true,"CabinClassCode":1,"MealCode":null,"OperatingAirline":{"Code":"QR","FlightNumber":null,"Equipment":"77W"},"SeatsRemaining":{"Number":9,"BelowMinimum":true},"IsCharter":false,"IsReturn":false}]}]},{"IsPassportMandatory":true,"TicketType":"eTicket","DirectionInd":1,"ValidatingAirlineCode":"QR","FareSourceCode":"353337383835263339263232303535","AirItineraryPricingInfo":{"FareType":2,"DivideInPartyIndicator":false,"ItinTotalFare":{"BaseFare":2358375.0,"TotalFare":5486325.0,"TotalCommission":124125.0,"TotalTax":3127950.0,"ServiceTax":0.0,"Currency":"IRR"},"PtcFareBreakdown":[{"PassengerFare":{"BaseFare":2358375.0,"TotalFare":5486325.0,"Commission":124125.0,"ServiceTax":0.0,"Surcharges":[],"Taxes":[{"Amount":3127950.0,"Currency":"IRR","TaxCode":""}],"Currency":"IRR"},"PassengerTypeQuantity":{"PassengerType":1,"Quantity":1},"FareBasisCodes":["OLAEP4NO"]}],"FareInfoes":[]},"OriginDestinationOptions":[{"FlightSegments":[{"DepartureDateTime":"2017-03-08T16:30:00","ArrivalDateTime":"2017-03-08T16:40:00","StopQuantity":0,"FlightNumber":"1017","ResBookDesigCode":"O","JourneyDuration":"01:10","DepartureAirportLocationCode":"DXB","ArrivalAirportLocationCode":"DOH","MarketingAirlineCode":"QR","MarriageGroup":null,"Eticket":true,"CabinClassCode":1,"MealCode":null,"OperatingAirline":{"Code":"QR","FlightNumber":null,"Equipment":"320"},"SeatsRemaining":{"Number":9,"BelowMinimum":true},"IsCharter":false,"IsReturn":false},{"DepartureDateTime":"2017-03-08T20:00:00","ArrivalDateTime":"2017-03-09T02:15:00","StopQuantity":0,"FlightNumber":"572","ResBookDesigCode":"O","JourneyDuration":"03:45","DepartureAirportLocationCode":"DOH","ArrivalAirportLocationCode":"BLR","MarketingAirlineCode":"QR","MarriageGroup":null,"Eticket":true,"CabinClassCode":1,"MealCode":null,"OperatingAirline":{"Code":"QR","FlightNumber":null,"Equipment":"77W"},"SeatsRemaining":{"Number":9,"BelowMinimum":true},"IsCharter":false,"IsReturn":false}]}]},{"IsPassportMandatory":true,"TicketType":"eTicket","DirectionInd":1,"ValidatingAirlineCode":"QR","FareSourceCode":"353337383836263339263232303535","AirItineraryPricingInfo":{"FareType":2,"DivideInPartyIndicator":false,"ItinTotalFare":{"BaseFare":2358375.0,"TotalFare":5486325.0,"TotalCommission":124125.0,"TotalTax":3127950.0,"ServiceTax":0.0,"Currency":"IRR"},"PtcFareBreakdown":[{"PassengerFare":{"BaseFare":2358375.0,"TotalFare":5486325.0,"Commission":124125.0,"ServiceTax":0.0,"Surcharges":[],"Taxes":[{"Amount":3127950.0,"Currency":"IRR","TaxCode":""}],"Currency":"IRR"},"PassengerTypeQuantity":{"PassengerType":1,"Quantity":1},"FareBasisCodes":["OLAEP4NO"]}],"FareInfoes":[]},"OriginDestinationOptions":[{"FlightSegments":[{"DepartureDateTime":"2017-03-08T15:30:00","ArrivalDateTime":"2017-03-08T15:40:00","StopQuantity":0,"FlightNumber":"1011","ResBookDesigCode":"O","JourneyDuration":"01:10","DepartureAirportLocationCode":"DXB","ArrivalAirportLocationCode":"DOH","MarketingAirlineCode":"QR","MarriageGroup":null,"Eticket":true,"CabinClassCode":1,"MealCode":null,"OperatingAirline":{"Code":"QR","FlightNumber":null,"Equipment":"320"},"SeatsRemaining":{"Number":9,"BelowMinimum":true},"IsCharter":false,"IsReturn":false},{"DepartureDateTime":"2017-03-08T20:00:00","ArrivalDateTime":"2017-03-09T02:15:00","StopQuantity":0,"FlightNumber":"572","ResBookDesigCode":"O","JourneyDuration":"03:45","DepartureAirportLocationCode":"DOH","ArrivalAirportLocationCode":"BLR","MarketingAirlineCode":"QR","MarriageGroup":null,"Eticket":true,"CabinClassCode":1,"MealCode":null,"OperatingAirline":{"Code":"QR","FlightNumber":null,"Equipment":"77W"},"SeatsRemaining":{"Number":9,"BelowMinimum":true},"IsCharter":false,"IsReturn":false}]}]},{"IsPassportMandatory":true,"TicketType":"eTicket","DirectionInd":1,"ValidatingAirlineCode":"9W","FareSourceCode":"353337383837263339263232303535","AirItineraryPricingInfo":{"FareType":2,"DivideInPartyIndicator":false,"ItinTotalFare":{"BaseFare":2184600.0,"TotalFare":5650170.0,"TotalCommission":0.0,"TotalTax":3465570.0,"ServiceTax":0.0,"Currency":"IRR"},"PtcFareBreakdown":[{"PassengerFare":{"BaseFare":2184600.0,"TotalFare":5650170.0,"Commission":0.0,"ServiceTax":0.0,"Surcharges":[],"Taxes":[{"Amount":3465570.0,"Currency":"IRR","TaxCode":""}],"Currency":"IRR"},"PassengerTypeQuantity":{"PassengerType":1,"Quantity":1},"FareBasisCodes":["W2LOWA1"]}],"FareInfoes":[]},"OriginDestinationOptions":[{"FlightSegments":[{"DepartureDateTime":"2017-03-08T12:15:00","ArrivalDateTime":"2017-03-08T16:45:00","StopQuantity":0,"FlightNumber":"541","ResBookDesigCode":"W","JourneyDuration":"03:00","DepartureAirportLocationCode":"DXB","ArrivalAirportLocationCode":"BOM","MarketingAirlineCode":"9W","MarriageGroup":null,"Eticket":true,"CabinClassCode":1,"MealCode":null,"OperatingAirline":{"Code":"9W","FlightNumber":null,"Equipment":"73H"},"SeatsRemaining":{"Number":9,"BelowMinimum":true},"IsCharter":false,"IsReturn":false},{"DepartureDateTime":"2017-03-08T18:15:00","ArrivalDateTime":"2017-03-08T19:50:00","StopQuantity":0,"FlightNumber":"483","ResBookDesigCode":"W","JourneyDuration":"01:35","DepartureAirportLocationCode":"BOM","ArrivalAirportLocationCode":"BLR","MarketingAirlineCode":"9W","MarriageGroup":null,"Eticket":true,"CabinClassCode":1,"MealCode":null,"OperatingAirline":{"Code":"9W","FlightNumber":null,"Equipment":"738"},"SeatsRemaining":{"Number":9,"BelowMinimum":true},"IsCharter":false,"IsReturn":false}]}]},{"IsPassportMandatory":true,"TicketType":"eTicket","DirectionInd":1,"ValidatingAirlineCode":"9W","FareSourceCode":"353337383838263339263232303535","AirItineraryPricingInfo":{"FareType":2,"DivideInPartyIndicator":false,"ItinTotalFare":{"BaseFare":2184600.0,"TotalFare":5650170.0,"TotalCommission":0.0,"TotalTax":3465570.0,"ServiceTax":0.0,"Currency":"IRR"},"PtcFareBreakdown":[{"PassengerFare":{"BaseFare":2184600.0,"TotalFare":5650170.0,"Commission":0.0,"ServiceTax":0.0,"Surcharges":[],"Taxes":[{"Amount":3465570.0,"Currency":"IRR","TaxCode":""}],"Currency":"IRR"},"PassengerTypeQuantity":{"PassengerType":1,"Quantity":1},"FareBasisCodes":["W2LOWA1"]}],"FareInfoes":[]},"OriginDestinationOptions":[{"FlightSegments":[{"DepartureDateTime":"2017-03-08T12:15:00","ArrivalDateTime":"2017-03-08T16:45:00","StopQuantity":0,"FlightNumber":"541","ResBookDesigCode":"W","JourneyDuration":"03:00","DepartureAirportLocationCode":"DXB","ArrivalAirportLocationCode":"BOM","MarketingAirlineCode":"9W","MarriageGroup":null,"Eticket":true,"CabinClassCode":1,"MealCode":null,"OperatingAirline":{"Code":"9W","FlightNumber":null,"Equipment":"73H"},"SeatsRemaining":{"Number":9,"BelowMinimum":true},"IsCharter":false,"IsReturn":false},{"DepartureDateTime":"2017-03-08T20:20:00","ArrivalDateTime":"2017-03-08T21:55:00","StopQuantity":0,"FlightNumber":"477","ResBookDesigCode":"W","JourneyDuration":"01:35","DepartureAirportLocationCode":"BOM","ArrivalAirportLocationCode":"BLR","MarketingAirlineCode":"9W","MarriageGroup":null,"Eticket":true,"CabinClassCode":1,"MealCode":null,"OperatingAirline":{"Code":"9W","FlightNumber":null,"Equipment":"738"},"SeatsRemaining":{"Number":9,"BelowMinimum":true},"IsCharter":false,"IsReturn":false}]}]},{"IsPassportMandatory":true,"TicketType":"eTicket","DirectionInd":1,"ValidatingAirlineCode":"9W","FareSourceCode":"353337383839263339263232303535","AirItineraryPricingInfo":{"FareType":2,"DivideInPartyIndicator":false,"ItinTotalFare":{"BaseFare":2184600.0,"TotalFare":5650170.0,"TotalCommission":0.0,"TotalTax":3465570.0,"ServiceTax":0.0,"Currency":"IRR"},"PtcFareBreakdown":[{"PassengerFare":{"BaseFare":2184600.0,"TotalFare":5650170.0,"Commission":0.0,"ServiceTax":0.0,"Surcharges":[],"Taxes":[{"Amount":3465570.0,"Currency":"IRR","TaxCode":""}],"Currency":"IRR"},"PassengerTypeQuantity":{"PassengerType":1,"Quantity":1},"FareBasisCodes":["W2LOWA1"]}],"FareInfoes":[]},"OriginDestinationOptions":[{"FlightSegments":[{"DepartureDateTime":"2017-03-08T22:30:00","ArrivalDateTime":"2017-03-09T03:00:00","StopQuantity":0,"FlightNumber":"543","ResBookDesigCode":"W","JourneyDuration":"03:00","DepartureAirportLocationCode":"DXB","ArrivalAirportLocationCode":"BOM","MarketingAirlineCode":"9W","MarriageGroup":null,"Eticket":true,"CabinClassCode":1,"MealCode":null,"OperatingAirline":{"Code":"9W","FlightNumber":null,"Equipment":"77W"},"SeatsRemaining":{"Number":9,"BelowMinimum":true},"IsCharter":false,"IsReturn":false},{"DepartureDateTime":"2017-03-09T06:35:00","ArrivalDateTime":"2017-03-09T08:10:00","StopQuantity":0,"FlightNumber":"411","ResBookDesigCode":"W","JourneyDuration":"01:35","DepartureAirportLocationCode":"BOM","ArrivalAirportLocationCode":"BLR","MarketingAirlineCode":"9W","MarriageGroup":null,"Eticket":true,"CabinClassCode":1,"MealCode":null,"OperatingAirline":{"Code":"9W","FlightNumber":null,"Equipment":"738"},"SeatsRemaining":{"Number":9,"BelowMinimum":true},"IsCharter":false,"IsReturn":false}]}]},{"IsPassportMandatory":true,"TicketType":"eTicket","DirectionInd":1,"ValidatingAirlineCode":"9W","FareSourceCode":"353337383930263339263232303535","AirItineraryPricingInfo":{"FareType":2,"DivideInPartyIndicator":false,"ItinTotalFare":{"BaseFare":2184600.0,"TotalFare":5650170.0,"TotalCommission":0.0,"TotalTax":3465570.0,"ServiceTax":0.0,"Currency":"IRR"},"PtcFareBreakdown":[{"PassengerFare":{"BaseFare":2184600.0,"TotalFare":5650170.0,"Commission":0.0,"ServiceTax":0.0,"Surcharges":[],"Taxes":[{"Amount":3465570.0,"Currency":"IRR","TaxCode":""}],"Currency":"IRR"},"PassengerTypeQuantity":{"PassengerType":1,"Quantity":1},"FareBasisCodes":["W2LOWA1"]}],"FareInfoes":[]},"OriginDestinationOptions":[{"FlightSegments":[{"DepartureDateTime":"2017-03-08T12:15:00","ArrivalDateTime":"2017-03-08T16:45:00","StopQuantity":0,"FlightNumber":"541","ResBookDesigCode":"W","JourneyDuration":"03:00","DepartureAirportLocationCode":"DXB","ArrivalAirportLocationCode":"BOM","MarketingAirlineCode":"9W","MarriageGroup":null,"Eticket":true,"CabinClassCode":1,"MealCode":null,"OperatingAirline":{"Code":"9W","FlightNumber":null,"Equipment":"73H"},"SeatsRemaining":{"Number":9,"BelowMinimum":true},"IsCharter":false,"IsReturn":false},{"DepartureDateTime":"2017-03-08T21:20:00","ArrivalDateTime":"2017-03-08T22:55:00","StopQuantity":0,"FlightNumber":"495","ResBookDesigCode":"W","JourneyDuration":"01:35","DepartureAirportLocationCode":"BOM","ArrivalAirportLocationCode":"BLR","MarketingAirlineCode":"9W","MarriageGroup":null,"Eticket":true,"CabinClassCode":1,"MealCode":null,"OperatingAirline":{"Code":"9W","FlightNumber":null,"Equipment":"738"},"SeatsRemaining":{"Number":9,"BelowMinimum":true},"IsCharter":false,"IsReturn":false}]}]},{"IsPassportMandatory":true,"TicketType":"eTicket","DirectionInd":1,"ValidatingAirlineCode":"G9","FareSourceCode":"353337383931263433263232303535","AirItineraryPricingInfo":{"FareType":4,"DivideInPartyIndicator":false,"ItinTotalFare":{"BaseFare":5475960.0,"TotalFare":5722092.0,"TotalCommission":0.0,"TotalTax":0.0,"ServiceTax":246132.0,"Currency":"IRR"},"PtcFareBreakdown":[{"PassengerFare":{"BaseFare":5475960.0,"TotalFare":5722092.0,"Commission":0.0,"ServiceTax":246132.0,"Surcharges":[],"Taxes":[{"Amount":0.0,"Currency":"IRR","TaxCode":""}],"Currency":"IRR"},"PassengerTypeQuantity":{"PassengerType":1,"Quantity":1},"FareBasisCodes":null}],"FareInfoes":[]},"OriginDestinationOptions":[{"FlightSegments":[{"DepartureDateTime":"2017-03-08T21:45:00","ArrivalDateTime":"2017-03-09T02:45:00","StopQuantity":0,"FlightNumber":"497","ResBookDesigCode":null,"JourneyDuration":"03:30","DepartureAirportLocationCode":"SHJ","ArrivalAirportLocationCode":"BLR","MarketingAirlineCode":"G9","MarriageGroup":"","Eticket":true,"CabinClassCode":1,"MealCode":"","OperatingAirline":{"Code":"G9","FlightNumber":"497","Equipment":""},"SeatsRemaining":{"Number":0,"BelowMinimum":true},"IsCharter":false,"IsReturn":false}]}]},{"IsPassportMandatory":true,"TicketType":"eTicket","DirectionInd":1,"ValidatingAirlineCode":"9W","FareSourceCode":"353337383932263339263232303535","AirItineraryPricingInfo":{"FareType":2,"DivideInPartyIndicator":false,"ItinTotalFare":{"BaseFare":2581800.0,"TotalFare":6047370.0,"TotalCommission":0.0,"TotalTax":3465570.0,"ServiceTax":0.0,"Currency":"IRR"},"PtcFareBreakdown":[{"PassengerFare":{"BaseFare":2581800.0,"TotalFare":6047370.0,"Commission":0.0,"ServiceTax":0.0,"Surcharges":[],"Taxes":[{"Amount":3465570.0,"Currency":"IRR","TaxCode":""}],"Currency":"IRR"},"PassengerTypeQuantity":{"PassengerType":1,"Quantity":1},"FareBasisCodes":["W2LOWA1"]}],"FareInfoes":[]},"OriginDestinationOptions":[{"FlightSegments":[{"DepartureDateTime":"2017-03-08T18:55:00","ArrivalDateTime":"2017-03-08T23:25:00","StopQuantity":0,"FlightNumber":"537","ResBookDesigCode":"W","JourneyDuration":"03:00","DepartureAirportLocationCode":"DXB","ArrivalAirportLocationCode":"BOM","MarketingAirlineCode":"9W","MarriageGroup":null,"Eticket":true,"CabinClassCode":1,"MealCode":null,"OperatingAirline":{"Code":"9W","FlightNumber":null,"Equipment":"73H"},"SeatsRemaining":{"Number":9,"BelowMinimum":true},"IsCharter":false,"IsReturn":false},{"DepartureDateTime":"2017-03-09T03:05:00","ArrivalDateTime":"2017-03-09T04:35:00","StopQuantity":0,"FlightNumber":"7145","ResBookDesigCode":"W","JourneyDuration":"01:30","DepartureAirportLocationCode":"BOM","ArrivalAirportLocationCode":"BLR","MarketingAirlineCode":"9W","MarriageGroup":null,"Eticket":true,"CabinClassCode":1,"MealCode":null,"OperatingAirline":{"Code":null,"FlightNumber":null,"Equipment":"73H"},"SeatsRemaining":{"Number":9,"BelowMinimum":true},"IsCharter":false,"IsReturn":false}]}]},{"IsPassportMandatory":true,"TicketType":"eTicket","DirectionInd":1,"ValidatingAirlineCode":"9W","FareSourceCode":"353337383933263339263232303535","AirItineraryPricingInfo":{"FareType":2,"DivideInPartyIndicator":false,"ItinTotalFare":{"BaseFare":2979000.0,"TotalFare":6444570.0,"TotalCommission":0.0,"TotalTax":3465570.0,"ServiceTax":0.0,"Currency":"IRR"},"PtcFareBreakdown":[{"PassengerFare":{"BaseFare":2979000.0,"TotalFare":6444570.0,"Commission":0.0,"ServiceTax":0.0,"Surcharges":[],"Taxes":[{"Amount":3465570.0,"Currency":"IRR","TaxCode":""}],"Currency":"IRR"},"PassengerTypeQuantity":{"PassengerType":1,"Quantity":1},"FareBasisCodes":["O2LOWA1"]}],"FareInfoes":[]},"OriginDestinationOptions":[{"FlightSegments":[{"DepartureDateTime":"2017-03-08T14:35:00","ArrivalDateTime":"2017-03-08T19:20:00","StopQuantity":0,"FlightNumber":"545","ResBookDesigCode":"O","JourneyDuration":"03:15","DepartureAirportLocationCode":"DXB","ArrivalAirportLocationCode":"DEL","MarketingAirlineCode":"9W","MarriageGroup":null,"Eticket":true,"CabinClassCode":1,"MealCode":null,"OperatingAirline":{"Code":"9W","FlightNumber":null,"Equipment":"73H"},"SeatsRemaining":{"Number":9,"BelowMinimum":true},"IsCharter":false,"IsReturn":false},{"DepartureDateTime":"2017-03-08T20:45:00","ArrivalDateTime":"2017-03-08T23:30:00","StopQuantity":0,"FlightNumber":"834","ResBookDesigCode":"O","JourneyDuration":"02:45","DepartureAirportLocationCode":"DEL","ArrivalAirportLocationCode":"BLR","MarketingAirlineCode":"9W","MarriageGroup":null,"Eticket":true,"CabinClassCode":1,"MealCode":null,"OperatingAirline":{"Code":"9W","FlightNumber":null,"Equipment":"73H"},"SeatsRemaining":{"Number":9,"BelowMinimum":true},"IsCharter":false,"IsReturn":false}]}]},{"IsPassportMandatory":true,"TicketType":"eTicket","DirectionInd":1,"ValidatingAirlineCode":"9W","FareSourceCode":"353337383934263339263232303535","AirItineraryPricingInfo":{"FareType":2,"DivideInPartyIndicator":false,"ItinTotalFare":{"BaseFare":2979000.0,"TotalFare":6444570.0,"TotalCommission":0.0,"TotalTax":3465570.0,"ServiceTax":0.0,"Currency":"IRR"},"PtcFareBreakdown":[{"PassengerFare":{"BaseFare":2979000.0,"TotalFare":6444570.0,"Commission":0.0,"ServiceTax":0.0,"Surcharges":[],"Taxes":[{"Amount":3465570.0,"Currency":"IRR","TaxCode":""}],"Currency":"IRR"},"PassengerTypeQuantity":{"PassengerType":1,"Quantity":1},"FareBasisCodes":["O2LOWA1"]}],"FareInfoes":[]},"OriginDestinationOptions":[{"FlightSegments":[{"DepartureDateTime":"2017-03-08T14:35:00","ArrivalDateTime":"2017-03-08T19:20:00","StopQuantity":0,"FlightNumber":"545","ResBookDesigCode":"O","JourneyDuration":"03:15","DepartureAirportLocationCode":"DXB","ArrivalAirportLocationCode":"DEL","MarketingAirlineCode":"9W","MarriageGroup":null,"Eticket":true,"CabinClassCode":1,"MealCode":null,"OperatingAirline":{"Code":"9W","FlightNumber":null,"Equipment":"73H"},"SeatsRemaining":{"Number":9,"BelowMinimum":true},"IsCharter":false,"IsReturn":false},{"DepartureDateTime":"2017-03-08T21:35:00","ArrivalDateTime":"2017-03-09T00:15:00","StopQuantity":0,"FlightNumber":"827","ResBookDesigCode":"O","JourneyDuration":"02:40","DepartureAirportLocationCode":"DEL","ArrivalAirportLocationCode":"BLR","MarketingAirlineCode":"9W","MarriageGroup":null,"Eticket":true,"CabinClassCode":1,"MealCode":null,"OperatingAirline":{"Code":"9W","FlightNumber":null,"Equipment":"738"},"SeatsRemaining":{"Number":9,"BelowMinimum":true},"IsCharter":false,"IsReturn":false}]}]},{"IsPassportMandatory":true,"TicketType":"eTicket","DirectionInd":1,"ValidatingAirlineCode":"9W","FareSourceCode":"353337383935263339263232303535","AirItineraryPricingInfo":{"FareType":2,"DivideInPartyIndicator":false,"ItinTotalFare":{"BaseFare":2979000.0,"TotalFare":6444570.0,"TotalCommission":0.0,"TotalTax":3465570.0,"ServiceTax":0.0,"Currency":"IRR"},"PtcFareBreakdown":[{"PassengerFare":{"BaseFare":2979000.0,"TotalFare":6444570.0,"Commission":0.0,"ServiceTax":0.0,"Surcharges":[],"Taxes":[{"Amount":3465570.0,"Currency":"IRR","TaxCode":""}],"Currency":"IRR"},"PassengerTypeQuantity":{"PassengerType":1,"Quantity":1},"FareBasisCodes":["O2LOWA1"]}],"FareInfoes":[]},"OriginDestinationOptions":[{"FlightSegments":[{"DepartureDateTime":"2017-03-08T23:00:00","ArrivalDateTime":"2017-03-09T03:40:00","StopQuantity":0,"FlightNumber":"547","ResBookDesigCode":"O","JourneyDuration":"03:10","DepartureAirportLocationCode":"DXB","ArrivalAirportLocationCode":"DEL","MarketingAirlineCode":"9W","MarriageGroup":null,"Eticket":true,"CabinClassCode":1,"MealCode":null,"OperatingAirline":{"Code":"9W","FlightNumber":null,"Equipment":"73H"},"SeatsRemaining":{"Number":9,"BelowMinimum":true},"IsCharter":false,"IsReturn":false},{"DepartureDateTime":"2017-03-09T07:00:00","ArrivalDateTime":"2017-03-09T09:45:00","StopQuantity":0,"FlightNumber":"807","ResBookDesigCode":"O","JourneyDuration":"02:45","DepartureAirportLocationCode":"DEL","ArrivalAirportLocationCode":"BLR","MarketingAirlineCode":"9W","MarriageGroup":null,"Eticket":true,"CabinClassCode":1,"MealCode":null,"OperatingAirline":{"Code":"9W","FlightNumber":null,"Equipment":"73H"},"SeatsRemaining":{"Number":9,"BelowMinimum":true},"IsCharter":false,"IsReturn":false}]}]},{"IsPassportMandatory":true,"TicketType":"eTicket","DirectionInd":1,"ValidatingAirlineCode":"9W","FareSourceCode":"353337383936263339263232303535","AirItineraryPricingInfo":{"FareType":2,"DivideInPartyIndicator":false,"ItinTotalFare":{"BaseFare":2979000.0,"TotalFare":6444570.0,"TotalCommission":0.0,"TotalTax":3465570.0,"ServiceTax":0.0,"Currency":"IRR"},"PtcFareBreakdown":[{"PassengerFare":{"BaseFare":2979000.0,"TotalFare":6444570.0,"Commission":0.0,"ServiceTax":0.0,"Surcharges":[],"Taxes":[{"Amount":3465570.0,"Currency":"IRR","TaxCode":""}],"Currency":"IRR"},"PassengerTypeQuantity":{"PassengerType":1,"Quantity":1},"FareBasisCodes":["O2LOWA1"]}],"FareInfoes":[]},"OriginDestinationOptions":[{"FlightSegments":[{"DepartureDateTime":"2017-03-08T05:45:00","ArrivalDateTime":"2017-03-08T10:30:00","StopQuantity":0,"FlightNumber":"587","ResBookDesigCode":"O","JourneyDuration":"03:15","DepartureAirportLocationCode":"DXB","ArrivalAirportLocationCode":"DEL","MarketingAirlineCode":"9W","MarriageGroup":null,"Eticket":true,"CabinClassCode":1,"MealCode":null,"OperatingAirline":{"Code":"9W","FlightNumber":null,"Equipment":"73H"},"SeatsRemaining":{"Number":9,"BelowMinimum":true},"IsCharter":false,"IsReturn":false},{"DepartureDateTime":"2017-03-08T14:35:00","ArrivalDateTime":"2017-03-08T17:20:00","StopQuantity":0,"FlightNumber":"823","ResBookDesigCode":"O","JourneyDuration":"02:45","DepartureAirportLocationCode":"DEL","ArrivalAirportLocationCode":"BLR","MarketingAirlineCode":"9W","MarriageGroup":null,"Eticket":true,"CabinClassCode":1,"MealCode":null,"OperatingAirline":{"Code":"9W","FlightNumber":null,"Equipment":"73H"},"SeatsRemaining":{"Number":9,"BelowMinimum":true},"IsCharter":false,"IsReturn":false}]}]},{"IsPassportMandatory":true,"TicketType":"eTicket","DirectionInd":1,"ValidatingAirlineCode":"UL","FareSourceCode":"353337383937263339263232303535","AirItineraryPricingInfo":{"FareType":2,"DivideInPartyIndicator":false,"ItinTotalFare":{"BaseFare":2681100.0,"TotalFare":6603450.0,"TotalCommission":0.0,"TotalTax":3922350.0,"ServiceTax":0.0,"Currency":"IRR"},"PtcFareBreakdown":[{"PassengerFare":{"BaseFare":2681100.0,"TotalFare":6603450.0,"Commission":0.0,"ServiceTax":0.0,"Surcharges":[],"Taxes":[{"Amount":3922350.0,"Currency":"IRR","TaxCode":""}],"Currency":"IRR"},"PassengerTypeQuantity":{"PassengerType":1,"Quantity":1},"FareBasisCodes":["QOW1AE"]}],"FareInfoes":[]},"OriginDestinationOptions":[{"FlightSegments":[{"DepartureDateTime":"2017-03-08T23:00:00","ArrivalDateTime":"2017-03-09T04:55:00","StopQuantity":0,"FlightNumber":"226","ResBookDesigCode":"Q","JourneyDuration":"04:25","DepartureAirportLocationCode":"DXB","ArrivalAirportLocationCode":"CMB","MarketingAirlineCode":"UL","MarriageGroup":null,"Eticket":true,"CabinClassCode":1,"MealCode":null,"OperatingAirline":{"Code":"UL","FlightNumber":null,"Equipment":"320"},"SeatsRemaining":{"Number":9,"BelowMinimum":true},"IsCharter":false,"IsReturn":false},{"DepartureDateTime":"2017-03-09T18:45:00","ArrivalDateTime":"2017-03-09T20:05:00","StopQuantity":0,"FlightNumber":"171","ResBookDesigCode":"Q","JourneyDuration":"01:20","DepartureAirportLocationCode":"CMB","ArrivalAirportLocationCode":"BLR","MarketingAirlineCode":"UL","MarriageGroup":null,"Eticket":true,"CabinClassCode":1,"MealCode":null,"OperatingAirline":{"Code":"UL","FlightNumber":null,"Equipment":"320"},"SeatsRemaining":{"Number":7,"BelowMinimum":true},"IsCharter":false,"IsReturn":false}]}]},{"IsPassportMandatory":true,"TicketType":"eTicket","DirectionInd":1,"ValidatingAirlineCode":"EK","FareSourceCode":"353337383938263339263232303535","AirItineraryPricingInfo":{"FareType":2,"DivideInPartyIndicator":false,"ItinTotalFare":{"BaseFare":3376200.0,"TotalFare":6802050.0,"TotalCommission":0.0,"TotalTax":3425850.0,"ServiceTax":0.0,"Currency":"IRR"},"PtcFareBreakdown":[{"PassengerFare":{"BaseFare":3376200.0,"TotalFare":6802050.0,"Commission":0.0,"ServiceTax":0.0,"Surcharges":[],"Taxes":[{"Amount":3425850.0,"Currency":"IRR","TaxCode":""}],"Currency":"IRR"},"PassengerTypeQuantity":{"PassengerType":1,"Quantity":1},"FareBasisCodes":["TXOWPAE1"]}],"FareInfoes":[]},"OriginDestinationOptions":[{"FlightSegments":[{"DepartureDateTime":"2017-03-08T13:35:00","ArrivalDateTime":"2017-03-08T18:35:00","StopQuantity":0,"FlightNumber":"566","ResBookDesigCode":"T","JourneyDuration":"03:30","DepartureAirportLocationCode":"DXB","ArrivalAirportLocationCode":"BLR","MarketingAirlineCode":"EK","MarriageGroup":null,"Eticket":true,"CabinClassCode":1,"MealCode":null,"OperatingAirline":{"Code":"EK","FlightNumber":null,"Equipment":"77W"},"SeatsRemaining":{"Number":7,"BelowMinimum":true},"IsCharter":false,"IsReturn":false}]}]},{"IsPassportMandatory":true,"TicketType":"eTicket","DirectionInd":1,"ValidatingAirlineCode":"EK","FareSourceCode":"353337383939263339263232303535","AirItineraryPricingInfo":{"FareType":2,"DivideInPartyIndicator":false,"ItinTotalFare":{"BaseFare":3376200.0,"TotalFare":6802050.0,"TotalCommission":0.0,"TotalTax":3425850.0,"ServiceTax":0.0,"Currency":"IRR"},"PtcFareBreakdown":[{"PassengerFare":{"BaseFare":3376200.0,"TotalFare":6802050.0,"Commission":0.0,"ServiceTax":0.0,"Surcharges":[],"Taxes":[{"Amount":3425850.0,"Currency":"IRR","TaxCode":""}],"Currency":"IRR"},"PassengerTypeQuantity":{"PassengerType":1,"Quantity":1},"FareBasisCodes":["TXOWPAE1"]}],"FareInfoes":[]},"OriginDestinationOptions":[{"FlightSegments":[{"DepartureDateTime":"2017-03-08T21:50:00","ArrivalDateTime":"2017-03-09T02:55:00","StopQuantity":0,"FlightNumber":"568","ResBookDesigCode":"T","JourneyDuration":"03:35","DepartureAirportLocationCode":"DXB","ArrivalAirportLocationCode":"BLR","MarketingAirlineCode":"EK","MarriageGroup":null,"Eticket":true,"CabinClassCode":1,"MealCode":null,"OperatingAirline":{"Code":"EK","FlightNumber":null,"Equipment":"77W"},"SeatsRemaining":{"Number":7,"BelowMinimum":true},"IsCharter":false,"IsReturn":false}]}]},{"IsPassportMandatory":true,"TicketType":"eTicket","DirectionInd":1,"ValidatingAirlineCode":"9W","FareSourceCode":"353337393030263339263232303535","AirItineraryPricingInfo":{"FareType":2,"DivideInPartyIndicator":false,"ItinTotalFare":{"BaseFare":4071300.0,"TotalFare":7536870.0,"TotalCommission":0.0,"TotalTax":3465570.0,"ServiceTax":0.0,"Currency":"IRR"},"PtcFareBreakdown":[{"PassengerFare":{"BaseFare":4071300.0,"TotalFare":7536870.0,"Commission":0.0,"ServiceTax":0.0,"Surcharges":[],"Taxes":[{"Amount":3465570.0,"Currency":"IRR","TaxCode":""}],"Currency":"IRR"},"PassengerTypeQuantity":{"PassengerType":1,"Quantity":1},"FareBasisCodes":["V2LOWA1"]}],"FareInfoes":[]},"OriginDestinationOptions":[{"FlightSegments":[{"DepartureDateTime":"2017-03-08T05:00:00","ArrivalDateTime":"2017-03-08T09:30:00","StopQuantity":0,"FlightNumber":"579","ResBookDesigCode":"V","JourneyDuration":"03:00","DepartureAirportLocationCode":"DXB","ArrivalAirportLocationCode":"BOM","MarketingAirlineCode":"9W","MarriageGroup":null,"Eticket":true,"CabinClassCode":1,"MealCode":null,"OperatingAirline":{"Code":"9W","FlightNumber":null,"Equipment":"73H"},"SeatsRemaining":{"Number":9,"BelowMinimum":true},"IsCharter":false,"IsReturn":false},{"DepartureDateTime":"2017-03-08T14:55:00","ArrivalDateTime":"2017-03-08T16:35:00","StopQuantity":0,"FlightNumber":"415","ResBookDesigCode":"V","JourneyDuration":"01:40","DepartureAirportLocationCode":"BOM","ArrivalAirportLocationCode":"BLR","MarketingAirlineCode":"9W","MarriageGroup":null,"Eticket":true,"CabinClassCode":1,"MealCode":null,"OperatingAirline":{"Code":"9W","FlightNumber":null,"Equipment":"73H"},"SeatsRemaining":{"Number":9,"BelowMinimum":true},"IsCharter":false,"IsReturn":false}]}]},{"IsPassportMandatory":true,"TicketType":"eTicket","DirectionInd":1,"ValidatingAirlineCode":"EK","FareSourceCode":"353337393031263339263232303535","AirItineraryPricingInfo":{"FareType":2,"DivideInPartyIndicator":false,"ItinTotalFare":{"BaseFare":4468500.0,"TotalFare":7894350.0,"TotalCommission":0.0,"TotalTax":3425850.0,"ServiceTax":0.0,"Currency":"IRR"},"PtcFareBreakdown":[{"PassengerFare":{"BaseFare":4468500.0,"TotalFare":7894350.0,"Commission":0.0,"ServiceTax":0.0,"Surcharges":[],"Taxes":[{"Amount":3425850.0,"Currency":"IRR","TaxCode":""}],"Currency":"IRR"},"PassengerTypeQuantity":{"PassengerType":1,"Quantity":1},"FareBasisCodes":["LXOWPAE1"]}],"FareInfoes":[]},"OriginDestinationOptions":[{"FlightSegments":[{"DepartureDateTime":"2017-03-08T03:40:00","ArrivalDateTime":"2017-03-08T08:50:00","StopQuantity":0,"FlightNumber":"564","ResBookDesigCode":"L","JourneyDuration":"03:40","DepartureAirportLocationCode":"DXB","ArrivalAirportLocationCode":"BLR","MarketingAirlineCode":"EK","MarriageGroup":null,"Eticket":true,"CabinClassCode":1,"MealCode":null,"OperatingAirline":{"Code":"EK","FlightNumber":null,"Equipment":"77W"},"SeatsRemaining":{"Number":7,"BelowMinimum":true},"IsCharter":false,"IsReturn":false}]}]},{"IsPassportMandatory":true,"TicketType":"eTicket","DirectionInd":1,"ValidatingAirlineCode":"AI","FareSourceCode":"353337393032263339263232303535","AirItineraryPricingInfo":{"FareType":2,"DivideInPartyIndicator":false,"ItinTotalFare":{"BaseFare":5163600.0,"TotalFare":9185250.0,"TotalCommission":0.0,"TotalTax":4021650.0,"ServiceTax":0.0,"Currency":"IRR"},"PtcFareBreakdown":[{"PassengerFare":{"BaseFare":5163600.0,"TotalFare":9185250.0,"Commission":0.0,"ServiceTax":0.0,"Surcharges":[],"Taxes":[{"Amount":4021650.0,"Currency":"IRR","TaxCode":""}],"Currency":"IRR"},"PassengerTypeQuantity":{"PassengerType":1,"Quantity":1},"FareBasisCodes":["ELOWAEBC","MIP"]}],"FareInfoes":[]},"OriginDestinationOptions":[{"FlightSegments":[{"DepartureDateTime":"2017-03-08T23:10:00","ArrivalDateTime":"2017-03-09T04:35:00","StopQuantity":0,"FlightNumber":"906","ResBookDesigCode":"E","JourneyDuration":"03:55","DepartureAirportLocationCode":"DXB","ArrivalAirportLocationCode":"MAA","MarketingAirlineCode":"AI","MarriageGroup":null,"Eticket":true,"CabinClassCode":1,"MealCode":null,"OperatingAirline":{"Code":"AI","FlightNumber":null,"Equipment":"321"},"SeatsRemaining":{"Number":5,"BelowMinimum":true},"IsCharter":false,"IsReturn":false},{"DepartureDateTime":"2017-03-09T14:20:00","ArrivalDateTime":"2017-03-09T15:20:00","StopQuantity":0,"FlightNumber":"563","ResBookDesigCode":"M","JourneyDuration":"01:00","DepartureAirportLocationCode":"MAA","ArrivalAirportLocationCode":"BLR","MarketingAirlineCode":"AI","MarriageGroup":null,"Eticket":true,"CabinClassCode":1,"MealCode":null,"OperatingAirline":{"Code":"AI","FlightNumber":null,"Equipment":"320"},"SeatsRemaining":{"Number":9,"BelowMinimum":true},"IsCharter":false,"IsReturn":false}]}]},{"IsPassportMandatory":true,"TicketType":"eTicket","DirectionInd":1,"ValidatingAirlineCode":"FZ","FareSourceCode":"353337393033263339263232303535","AirItineraryPricingInfo":{"FareType":2,"DivideInPartyIndicator":false,"ItinTotalFare":{"BaseFare":10426500.0,"TotalFare":11618100.0,"TotalCommission":0.0,"TotalTax":1191600.0,"ServiceTax":0.0,"Currency":"IRR"},"PtcFareBreakdown":[{"PassengerFare":{"BaseFare":10426500.0,"TotalFare":11618100.0,"Commission":0.0,"ServiceTax":0.0,"Surcharges":[],"Taxes":[{"Amount":1191600.0,"Currency":"IRR","TaxCode":""}],"Currency":"IRR"},"PassengerTypeQuantity":{"PassengerType":1,"Quantity":1},"FareBasisCodes":["WOW2AE1"]}],"FareInfoes":[]},"OriginDestinationOptions":[{"FlightSegments":[{"DepartureDateTime":"2017-03-08T20:45:00","ArrivalDateTime":"2017-03-09T02:30:00","StopQuantity":0,"FlightNumber":"439","ResBookDesigCode":"W","JourneyDuration":"04:15","DepartureAirportLocationCode":"DXB","ArrivalAirportLocationCode":"TRV","MarketingAirlineCode":"FZ","MarriageGroup":null,"Eticket":true,"CabinClassCode":1,"MealCode":null,"OperatingAirline":{"Code":"FZ","FlightNumber":null,"Equipment":"73H"},"SeatsRemaining":{"Number":4,"BelowMinimum":true},"IsCharter":false,"IsReturn":false},{"DepartureDateTime":"2017-03-09T05:45:00","ArrivalDateTime":"2017-03-09T06:55:00","StopQuantity":0,"FlightNumber":"824","ResBookDesigCode":"W","JourneyDuration":"01:10","DepartureAirportLocationCode":"TRV","ArrivalAirportLocationCode":"BLR","MarketingAirlineCode":"9W","MarriageGroup":null,"Eticket":true,"CabinClassCode":1,"MealCode":null,"OperatingAirline":{"Code":"9W","FlightNumber":null,"Equipment":"73H"},"SeatsRemaining":{"Number":9,"BelowMinimum":true},"IsCharter":false,"IsReturn":false}]}]},{"IsPassportMandatory":true,"TicketType":"eTicket","DirectionInd":1,"ValidatingAirlineCode":"AI","FareSourceCode":"353337393034263339263232303535","AirItineraryPricingInfo":{"FareType":2,"DivideInPartyIndicator":false,"ItinTotalFare":{"BaseFare":8440500.0,"TotalFare":13753050.0,"TotalCommission":0.0,"TotalTax":5312550.0,"ServiceTax":0.0,"Currency":"IRR"},"PtcFareBreakdown":[{"PassengerFare":{"BaseFare":8440500.0,"TotalFare":13753050.0,"Commission":0.0,"ServiceTax":0.0,"Surcharges":[],"Taxes":[{"Amount":5312550.0,"Currency":"IRR","TaxCode":""}],"Currency":"IRR"},"PassengerTypeQuantity":{"PassengerType":1,"Quantity":1},"FareBasisCodes":["LLOWAEBB","MIP"]}],"FareInfoes":[]},"OriginDestinationOptions":[{"FlightSegments":[{"DepartureDateTime":"2017-03-08T23:40:00","ArrivalDateTime":"2017-03-09T04:10:00","StopQuantity":0,"FlightNumber":"984","ResBookDesigCode":"L","JourneyDuration":"03:00","DepartureAirportLocationCode":"DXB","ArrivalAirportLocationCode":"BOM","MarketingAirlineCode":"AI","MarriageGroup":null,"Eticket":true,"CabinClassCode":1,"MealCode":null,"OperatingAirline":{"Code":"AI","FlightNumber":null,"Equipment":"321"},"SeatsRemaining":{"Number":4,"BelowMinimum":true},"IsCharter":false,"IsReturn":false},{"DepartureDateTime":"2017-03-09T06:15:00","ArrivalDateTime":"2017-03-09T07:50:00","StopQuantity":0,"FlightNumber":"603","ResBookDesigCode":"M","JourneyDuration":"01:35","DepartureAirportLocationCode":"BOM","ArrivalAirportLocationCode":"BLR","MarketingAirlineCode":"AI","MarriageGroup":null,"Eticket":true,"CabinClassCode":1,"MealCode":null,"OperatingAirline":{"Code":"AI","FlightNumber":null,"Equipment":"321"},"SeatsRemaining":{"Number":9,"BelowMinimum":true},"IsCharter":false,"IsReturn":false}]}]},{"IsPassportMandatory":true,"TicketType":"eTicket","DirectionInd":1,"ValidatingAirlineCode":"AI","FareSourceCode":"353337393035263339263232303535","AirItineraryPricingInfo":{"FareType":2,"DivideInPartyIndicator":false,"ItinTotalFare":{"BaseFare":8440500.0,"TotalFare":13753050.0,"TotalCommission":0.0,"TotalTax":5312550.0,"ServiceTax":0.0,"Currency":"IRR"},"PtcFareBreakdown":[{"PassengerFare":{"BaseFare":8440500.0,"TotalFare":13753050.0,"Commission":0.0,"ServiceTax":0.0,"Surcharges":[],"Taxes":[{"Amount":5312550.0,"Currency":"IRR","TaxCode":""}],"Currency":"IRR"},"PassengerTypeQuantity":{"PassengerType":1,"Quantity":1},"FareBasisCodes":["LLOWAEBB","MIP"]}],"FareInfoes":[]},"OriginDestinationOptions":[{"FlightSegments":[{"DepartureDateTime":"2017-03-08T23:40:00","ArrivalDateTime":"2017-03-09T04:10:00","StopQuantity":0,"FlightNumber":"984","ResBookDesigCode":"L","JourneyDuration":"03:00","DepartureAirportLocationCode":"DXB","ArrivalAirportLocationCode":"BOM","MarketingAirlineCode":"AI","MarriageGroup":null,"Eticket":true,"CabinClassCode":1,"MealCode":null,"OperatingAirline":{"Code":"AI","FlightNumber":null,"Equipment":"321"},"SeatsRemaining":{"Number":4,"BelowMinimum":true},"IsCharter":false,"IsReturn":false},{"DepartureDateTime":"2017-03-09T09:10:00","ArrivalDateTime":"2017-03-09T11:00:00","StopQuantity":0,"FlightNumber":"639","ResBookDesigCode":"M","JourneyDuration":"01:50","DepartureAirportLocationCode":"BOM","ArrivalAirportLocationCode":"BLR","MarketingAirlineCode":"AI","MarriageGroup":null,"Eticket":true,"CabinClassCode":1,"MealCode":null,"OperatingAirline":{"Code":"AI","FlightNumber":null,"Equipment":"320"},"SeatsRemaining":{"Number":9,"BelowMinimum":true},"IsCharter":false,"IsReturn":false}]}]},{"IsPassportMandatory":true,"TicketType":"eTicket","DirectionInd":1,"ValidatingAirlineCode":"AI","FareSourceCode":"353337393036263339263232303535","AirItineraryPricingInfo":{"FareType":2,"DivideInPartyIndicator":false,"ItinTotalFare":{"BaseFare":10923000.0,"TotalFare":14845350.0,"TotalCommission":0.0,"TotalTax":3922350.0,"ServiceTax":0.0,"Currency":"IRR"},"PtcFareBreakdown":[{"PassengerFare":{"BaseFare":10923000.0,"TotalFare":14845350.0,"Commission":0.0,"ServiceTax":0.0,"Surcharges":[],"Taxes":[{"Amount":3922350.0,"Currency":"IRR","TaxCode":""}],"Currency":"IRR"},"PassengerTypeQuantity":{"PassengerType":1,"Quantity":1},"FareBasisCodes":["SLOWAEBA","MIP"]}],"FareInfoes":[]},"OriginDestinationOptions":[{"FlightSegments":[{"DepartureDateTime":"2017-03-08T00:05:00","ArrivalDateTime":"2017-03-08T04:45:00","StopQuantity":0,"FlightNumber":"996","ResBookDesigCode":"S","JourneyDuration":"03:10","DepartureAirportLocationCode":"DXB","ArrivalAirportLocationCode":"DEL","MarketingAirlineCode":"AI","MarriageGroup":null,"Eticket":true,"CabinClassCode":1,"MealCode":null,"OperatingAirline":{"Code":"AI","FlightNumber":null,"Equipment":"788"},"SeatsRemaining":{"Number":7,"BelowMinimum":true},"IsCharter":false,"IsReturn":false},{"DepartureDateTime":"2017-03-08T06:15:00","ArrivalDateTime":"2017-03-08T09:10:00","StopQuantity":0,"FlightNumber":"803","ResBookDesigCode":"M","JourneyDuration":"02:55","DepartureAirportLocationCode":"DEL","ArrivalAirportLocationCode":"BLR","MarketingAirlineCode":"AI","MarriageGroup":null,"Eticket":true,"CabinClassCode":1,"MealCode":null,"OperatingAirline":{"Code":"AI","FlightNumber":null,"Equipment":"321"},"SeatsRemaining":{"Number":9,"BelowMinimum":true},"IsCharter":false,"IsReturn":false}]}]},{"IsPassportMandatory":true,"TicketType":"eTicket","DirectionInd":1,"ValidatingAirlineCode":"WY","FareSourceCode":"353337393037263339263232303535","AirItineraryPricingInfo":{"FareType":2,"DivideInPartyIndicator":false,"ItinTotalFare":{"BaseFare":14795700.0,"TotalFare":16235550.0,"TotalCommission":0.0,"TotalTax":1439850.0,"ServiceTax":0.0,"Currency":"IRR"},"PtcFareBreakdown":[{"PassengerFare":{"BaseFare":14795700.0,"TotalFare":16235550.0,"Commission":0.0,"ServiceTax":0.0,"Surcharges":[],"Taxes":[{"Amount":1439850.0,"Currency":"IRR","TaxCode":""}],"Currency":"IRR"},"PassengerTypeQuantity":{"PassengerType":1,"Quantity":1},"FareBasisCodes":["KFEOWAE"]}],"FareInfoes":[]},"OriginDestinationOptions":[{"FlightSegments":[{"DepartureDateTime":"2017-03-08T02:45:00","ArrivalDateTime":"2017-03-08T03:55:00","StopQuantity":0,"FlightNumber":"5866","ResBookDesigCode":"K","JourneyDuration":"01:10","DepartureAirportLocationCode":"DXB","ArrivalAirportLocationCode":"MCT","MarketingAirlineCode":"WY","MarriageGroup":null,"Eticket":true,"CabinClassCode":1,"MealCode":null,"OperatingAirline":{"Code":"EK","FlightNumber":null,"Equipment":"332"},"SeatsRemaining":{"Number":4,"BelowMinimum":true},"IsCharter":false,"IsReturn":false},{"DepartureDateTime":"2017-03-08T08:50:00","ArrivalDateTime":"2017-03-08T13:40:00","StopQuantity":0,"FlightNumber":"283","ResBookDesigCode":"K","JourneyDuration":"03:20","DepartureAirportLocationCode":"MCT","ArrivalAirportLocationCode":"BLR","MarketingAirlineCode":"WY","MarriageGroup":null,"Eticket":true,"CabinClassCode":1,"MealCode":null,"OperatingAirline":{"Code":"WY","FlightNumber":null,"Equipment":"738"},"SeatsRemaining":{"Number":4,"BelowMinimum":true},"IsCharter":false,"IsReturn":false}]}]},{"IsPassportMandatory":true,"TicketType":"eTicket","DirectionInd":1,"ValidatingAirlineCode":"MH","FareSourceCode":"353337393038263339263232303535","AirItineraryPricingInfo":{"FareType":2,"DivideInPartyIndicator":false,"ItinTotalFare":{"BaseFare":15590100.0,"TotalFare":16732050.0,"TotalCommission":0.0,"TotalTax":1141950.0,"ServiceTax":0.0,"Currency":"IRR"},"PtcFareBreakdown":[{"PassengerFare":{"BaseFare":15590100.0,"TotalFare":16732050.0,"Commission":0.0,"ServiceTax":0.0,"Surcharges":[],"Taxes":[{"Amount":1141950.0,"Currency":"IRR","TaxCode":""}],"Currency":"IRR"},"PassengerTypeQuantity":{"PassengerType":1,"Quantity":1},"FareBasisCodes":["NBCOWAE"]}],"FareInfoes":[]},"OriginDestinationOptions":[{"FlightSegments":[{"DepartureDateTime":"2017-03-08T04:10:00","ArrivalDateTime":"2017-03-08T15:15:00","StopQuantity":0,"FlightNumber":"4502","ResBookDesigCode":"N","JourneyDuration":"07:05","DepartureAirportLocationCode":"DXB","ArrivalAirportLocationCode":"KUL","MarketingAirlineCode":"MH","MarriageGroup":null,"Eticket":true,"CabinClassCode":1,"MealCode":null,"OperatingAirline":{"Code":"EK","FlightNumber":null,"Equipment":"777"},"SeatsRemaining":{"Number":9,"BelowMinimum":true},"IsCharter":false,"IsReturn":false},{"DepartureDateTime":"2017-03-08T22:00:00","ArrivalDateTime":"2017-03-08T23:30:00","StopQuantity":0,"FlightNumber":"192","ResBookDesigCode":"N","JourneyDuration":"04:00","DepartureAirportLocationCode":"KUL","ArrivalAirportLocationCode":"BLR","MarketingAirlineCode":"MH","MarriageGroup":null,"Eticket":true,"CabinClassCode":1,"MealCode":null,"OperatingAirline":{"Code":"MH","FlightNumber":null,"Equipment":"738"},"SeatsRemaining":{"Number":9,"BelowMinimum":true},"IsCharter":false,"IsReturn":false}]}]},{"IsPassportMandatory":true,"TicketType":"eTicket","DirectionInd":1,"ValidatingAirlineCode":"SQ","FareSourceCode":"353337393039263339263232303535","AirItineraryPricingInfo":{"FareType":8,"DivideInPartyIndicator":false,"ItinTotalFare":{"BaseFare":12909000.0,"TotalFare":22193550.0,"TotalCommission":0.0,"TotalTax":9284550.0,"ServiceTax":0.0,"Currency":"IRR"},"PtcFareBreakdown":[{"PassengerFare":{"BaseFare":12909000.0,"TotalFare":22193550.0,"Commission":0.0,"ServiceTax":0.0,"Surcharges":[],"Taxes":[{"Amount":9284550.0,"Currency":"IRR","TaxCode":""}],"Currency":"IRR"},"PassengerTypeQuantity":{"PassengerType":1,"Quantity":1},"FareBasisCodes":["NOWINAE"]}],"FareInfoes":[]},"OriginDestinationOptions":[{"FlightSegments":[{"DepartureDateTime":"2017-03-08T20:00:00","ArrivalDateTime":"2017-03-09T07:15:00","StopQuantity":0,"FlightNumber":"495","ResBookDesigCode":"N","JourneyDuration":"07:15","DepartureAirportLocationCode":"DXB","ArrivalAirportLocationCode":"SIN","MarketingAirlineCode":"SQ","MarriageGroup":null,"Eticket":true,"CabinClassCode":1,"MealCode":null,"OperatingAirline":{"Code":"SQ","FlightNumber":null,"Equipment":"77W"},"SeatsRemaining":{"Number":9,"BelowMinimum":true},"IsCharter":false,"IsReturn":false},{"DepartureDateTime":"2017-03-09T20:05:00","ArrivalDateTime":"2017-03-09T21:55:00","StopQuantity":0,"FlightNumber":"502","ResBookDesigCode":"N","JourneyDuration":"04:20","DepartureAirportLocationCode":"SIN","ArrivalAirportLocationCode":"BLR","MarketingAirlineCode":"SQ","MarriageGroup":null,"Eticket":true,"CabinClassCode":1,"MealCode":null,"OperatingAirline":{"Code":"SQ","FlightNumber":null,"Equipment":"772"},"SeatsRemaining":{"Number":9,"BelowMinimum":true},"IsCharter":false,"IsReturn":false}]}]},{"IsPassportMandatory":true,"TicketType":"eTicket","DirectionInd":1,"ValidatingAirlineCode":"AI","FareSourceCode":"353337393130263339263232303535","AirItineraryPricingInfo":{"FareType":2,"DivideInPartyIndicator":false,"ItinTotalFare":{"BaseFare":41606700.0,"TotalFare":47316450.0,"TotalCommission":0.0,"TotalTax":5709750.0,"ServiceTax":0.0,"Currency":"IRR"},"PtcFareBreakdown":[{"PassengerFare":{"BaseFare":41606700.0,"TotalFare":47316450.0,"Commission":0.0,"ServiceTax":0.0,"Surcharges":[],"Taxes":[{"Amount":5709750.0,"Currency":"IRR","TaxCode":""}],"Currency":"IRR"},"PassengerTypeQuantity":{"PassengerType":1,"Quantity":1},"FareBasisCodes":["YIF"]}],"FareInfoes":[]},"OriginDestinationOptions":[{"FlightSegments":[{"DepartureDateTime":"2017-03-08T23:10:00","ArrivalDateTime":"2017-03-09T04:35:00","StopQuantity":0,"FlightNumber":"906","ResBookDesigCode":"Y","JourneyDuration":"03:55","DepartureAirportLocationCode":"DXB","ArrivalAirportLocationCode":"MAA","MarketingAirlineCode":"AI","MarriageGroup":null,"Eticket":true,"CabinClassCode":1,"MealCode":null,"OperatingAirline":{"Code":"AI","FlightNumber":null,"Equipment":"321"},"SeatsRemaining":{"Number":9,"BelowMinimum":true},"IsCharter":false,"IsReturn":false},{"DepartureDateTime":"2017-03-09T06:50:00","ArrivalDateTime":"2017-03-09T07:55:00","StopQuantity":0,"FlightNumber":"2753","ResBookDesigCode":"Y","JourneyDuration":"01:05","DepartureAirportLocationCode":"MAA","ArrivalAirportLocationCode":"BLR","MarketingAirlineCode":"9W","MarriageGroup":null,"Eticket":true,"CabinClassCode":1,"MealCode":null,"OperatingAirline":{"Code":"9W","FlightNumber":null,"Equipment":"AT7"},"SeatsRemaining":{"Number":9,"BelowMinimum":true},"IsCharter":false,"IsReturn":false}]}]},{"IsPassportMandatory":true,"TicketType":"eTicket","DirectionInd":1,"ValidatingAirlineCode":"AI","FareSourceCode":"353337393131263339263232303535","AirItineraryPricingInfo":{"FareType":2,"DivideInPartyIndicator":false,"ItinTotalFare":{"BaseFare":41606700.0,"TotalFare":47316450.0,"TotalCommission":0.0,"TotalTax":5709750.0,"ServiceTax":0.0,"Currency":"IRR"},"PtcFareBreakdown":[{"PassengerFare":{"BaseFare":41606700.0,"TotalFare":47316450.0,"Commission":0.0,"ServiceTax":0.0,"Surcharges":[],"Taxes":[{"Amount":5709750.0,"Currency":"IRR","TaxCode":""}],"Currency":"IRR"},"PassengerTypeQuantity":{"PassengerType":1,"Quantity":1},"FareBasisCodes":["YIF"]}],"FareInfoes":[]},"OriginDestinationOptions":[{"FlightSegments":[{"DepartureDateTime":"2017-03-08T23:10:00","ArrivalDateTime":"2017-03-09T04:35:00","StopQuantity":0,"FlightNumber":"906","ResBookDesigCode":"Y","JourneyDuration":"03:55","DepartureAirportLocationCode":"DXB","ArrivalAirportLocationCode":"MAA","MarketingAirlineCode":"AI","MarriageGroup":null,"Eticket":true,"CabinClassCode":1,"MealCode":null,"OperatingAirline":{"Code":"AI","FlightNumber":null,"Equipment":"321"},"SeatsRemaining":{"Number":9,"BelowMinimum":true},"IsCharter":false,"IsReturn":false},{"DepartureDateTime":"2017-03-09T09:15:00","ArrivalDateTime":"2017-03-09T10:20:00","StopQuantity":0,"FlightNumber":"2301","ResBookDesigCode":"Y","JourneyDuration":"01:05","DepartureAirportLocationCode":"MAA","ArrivalAirportLocationCode":"BLR","MarketingAirlineCode":"9W","MarriageGroup":null,"Eticket":true,"CabinClassCode":1,"MealCode":null,"OperatingAirline":{"Code":"9W","FlightNumber":null,"Equipment":"AT7"},"SeatsRemaining":{"Number":9,"BelowMinimum":true},"IsCharter":false,"IsReturn":false}]}]},{"IsPassportMandatory":true,"TicketType":"eTicket","DirectionInd":1,"ValidatingAirlineCode":"AI","FareSourceCode":"353337393132263339263232303535","AirItineraryPricingInfo":{"FareType":2,"DivideInPartyIndicator":false,"ItinTotalFare":{"BaseFare":41606700.0,"TotalFare":47415750.0,"TotalCommission":0.0,"TotalTax":5809050.0,"ServiceTax":0.0,"Currency":"IRR"},"PtcFareBreakdown":[{"PassengerFare":{"BaseFare":41606700.0,"TotalFare":47415750.0,"Commission":0.0,"ServiceTax":0.0,"Surcharges":[],"Taxes":[{"Amount":5809050.0,"Currency":"IRR","TaxCode":""}],"Currency":"IRR"},"PassengerTypeQuantity":{"PassengerType":1,"Quantity":1},"FareBasisCodes":["YIF"]}],"FareInfoes":[]},"OriginDestinationOptions":[{"FlightSegments":[{"DepartureDateTime":"2017-03-08T23:40:00","ArrivalDateTime":"2017-03-09T04:10:00","StopQuantity":0,"FlightNumber":"984","ResBookDesigCode":"Y","JourneyDuration":"03:00","DepartureAirportLocationCode":"DXB","ArrivalAirportLocationCode":"BOM","MarketingAirlineCode":"AI","MarriageGroup":null,"Eticket":true,"CabinClassCode":1,"MealCode":null,"OperatingAirline":{"Code":"AI","FlightNumber":null,"Equipment":"321"},"SeatsRemaining":{"Number":9,"BelowMinimum":true},"IsCharter":false,"IsReturn":false},{"DepartureDateTime":"2017-03-09T09:00:00","ArrivalDateTime":"2017-03-09T10:35:00","StopQuantity":0,"FlightNumber":"397","ResBookDesigCode":"Y","JourneyDuration":"01:35","DepartureAirportLocationCode":"BOM","ArrivalAirportLocationCode":"BLR","MarketingAirlineCode":"9W","MarriageGroup":null,"Eticket":true,"CabinClassCode":1,"MealCode":null,"OperatingAirline":{"Code":"9W","FlightNumber":null,"Equipment":"738"},"SeatsRemaining":{"Number":9,"BelowMinimum":true},"IsCharter":false,"IsReturn":false}]}]},{"IsPassportMandatory":true,"TicketType":"eTicket","DirectionInd":1,"ValidatingAirlineCode":"AI","FareSourceCode":"353337393133263339263232303535","AirItineraryPricingInfo":{"FareType":2,"DivideInPartyIndicator":false,"ItinTotalFare":{"BaseFare":41606700.0,"TotalFare":47614350.0,"TotalCommission":0.0,"TotalTax":6007650.0,"ServiceTax":0.0,"Currency":"IRR"},"PtcFareBreakdown":[{"PassengerFare":{"BaseFare":41606700.0,"TotalFare":47614350.0,"Commission":0.0,"ServiceTax":0.0,"Surcharges":[],"Taxes":[{"Amount":6007650.0,"Currency":"IRR","TaxCode":""}],"Currency":"IRR"},"PassengerTypeQuantity":{"PassengerType":1,"Quantity":1},"FareBasisCodes":["YIF"]}],"FareInfoes":[]},"OriginDestinationOptions":[{"FlightSegments":[{"DepartureDateTime":"2017-03-08T00:30:00","ArrivalDateTime":"2017-03-08T05:30:00","StopQuantity":0,"FlightNumber":"952","ResBookDesigCode":"Y","JourneyDuration":"03:30","DepartureAirportLocationCode":"DXB","ArrivalAirportLocationCode":"HYD","MarketingAirlineCode":"AI","MarriageGroup":null,"Eticket":true,"CabinClassCode":1,"MealCode":null,"OperatingAirline":{"Code":"AI","FlightNumber":null,"Equipment":"321"},"SeatsRemaining":{"Number":9,"BelowMinimum":true},"IsCharter":false,"IsReturn":false},{"DepartureDateTime":"2017-03-08T07:50:00","ArrivalDateTime":"2017-03-08T08:55:00","StopQuantity":0,"FlightNumber":"2742","ResBookDesigCode":"Y","JourneyDuration":"01:05","DepartureAirportLocationCode":"HYD","ArrivalAirportLocationCode":"BLR","MarketingAirlineCode":"9W","MarriageGroup":null,"Eticket":true,"CabinClassCode":1,"MealCode":null,"OperatingAirline":{"Code":"9W","FlightNumber":null,"Equipment":"738"},"SeatsRemaining":{"Number":9,"BelowMinimum":true},"IsCharter":false,"IsReturn":false}]}]},{"IsPassportMandatory":true,"TicketType":"eTicket","DirectionInd":1,"ValidatingAirlineCode":"MJ","FareSourceCode":"353337393134263339263232303535","AirItineraryPricingInfo":{"FareType":2,"DivideInPartyIndicator":false,"ItinTotalFare":{"BaseFare":52033200.0,"TotalFare":53175150.0,"TotalCommission":0.0,"TotalTax":1141950.0,"ServiceTax":0.0,"Currency":"IRR"},"PtcFareBreakdown":[{"PassengerFare":{"BaseFare":52033200.0,"TotalFare":53175150.0,"Commission":0.0,"ServiceTax":0.0,"Surcharges":[],"Taxes":[{"Amount":1141950.0,"Currency":"IRR","TaxCode":""}],"Currency":"IRR"},"PassengerTypeQuantity":{"PassengerType":1,"Quantity":1},"FareBasisCodes":["YIF"]}],"FareInfoes":[]},"OriginDestinationOptions":[{"FlightSegments":[{"DepartureDateTime":"2017-03-08T22:50:00","ArrivalDateTime":"2017-03-09T05:00:00","StopQuantity":0,"FlightNumber":"2226","ResBookDesigCode":"Y","JourneyDuration":"04:40","DepartureAirportLocationCode":"DXB","ArrivalAirportLocationCode":"CMB","MarketingAirlineCode":"MJ","MarriageGroup":null,"Eticket":true,"CabinClassCode":1,"MealCode":null,"OperatingAirline":{"Code":"UL","FlightNumber":null,"Equipment":"332"},"SeatsRemaining":{"Number":5,"BelowMinimum":true},"IsCharter":false,"IsReturn":false},{"DepartureDateTime":"2017-03-09T18:45:00","ArrivalDateTime":"2017-03-09T20:05:00","StopQuantity":0,"FlightNumber":"2171","ResBookDesigCode":"Y","JourneyDuration":"01:20","DepartureAirportLocationCode":"CMB","ArrivalAirportLocationCode":"BLR","MarketingAirlineCode":"MJ","MarriageGroup":null,"Eticket":true,"CabinClassCode":1,"MealCode":null,"OperatingAirline":{"Code":"UL","FlightNumber":null,"Equipment":"320"},"SeatsRemaining":{"Number":9,"BelowMinimum":true},"IsCharter":false,"IsReturn":false}]}]},{"IsPassportMandatory":true,"TicketType":"eTicket","DirectionInd":1,"ValidatingAirlineCode":"BA","FareSourceCode":"353337393135263339263232303535","AirItineraryPricingInfo":{"FareType":2,"DivideInPartyIndicator":false,"ItinTotalFare":{"BaseFare":69212100.0,"TotalFare":80184750.0,"TotalCommission":0.0,"TotalTax":10972650.0,"ServiceTax":0.0,"Currency":"IRR"},"PtcFareBreakdown":[{"PassengerFare":{"BaseFare":69212100.0,"TotalFare":80184750.0,"Commission":0.0,"ServiceTax":0.0,"Surcharges":[],"Taxes":[{"Amount":10972650.0,"Currency":"IRR","TaxCode":""}],"Currency":"IRR"},"PassengerTypeQuantity":{"PassengerType":1,"Quantity":1},"FareBasisCodes":["HLFFME","Y2BA"]}],"FareInfoes":[]},"OriginDestinationOptions":[{"FlightSegments":[{"DepartureDateTime":"2017-03-08T02:25:00","ArrivalDateTime":"2017-03-08T06:25:00","StopQuantity":0,"FlightNumber":"106","ResBookDesigCode":"H","JourneyDuration":"08:00","DepartureAirportLocationCode":"DXB","ArrivalAirportLocationCode":"LHR","MarketingAirlineCode":"BA","MarriageGroup":null,"Eticket":true,"CabinClassCode":1,"MealCode":null,"OperatingAirline":{"Code":"BA","FlightNumber":null,"Equipment":"744"},"SeatsRemaining":{"Number":9,"BelowMinimum":true},"IsCharter":false,"IsReturn":false},{"DepartureDateTime":"2017-03-08T14:00:00","ArrivalDateTime":"2017-03-09T05:00:00","StopQuantity":0,"FlightNumber":"119","ResBookDesigCode":"Y","JourneyDuration":"09:30","DepartureAirportLocationCode":"LHR","ArrivalAirportLocationCode":"BLR","MarketingAirlineCode":"BA","MarriageGroup":null,"Eticket":true,"CabinClassCode":1,"MealCode":null,"OperatingAirline":{"Code":"BA","FlightNumber":null,"Equipment":"777"},"SeatsRemaining":{"Number":9,"BelowMinimum":true},"IsCharter":false,"IsReturn":false}]}]},{"IsPassportMandatory":true,"TicketType":"eTicket","DirectionInd":1,"ValidatingAirlineCode":"TG","FareSourceCode":"353337393136263339263232303535","AirItineraryPricingInfo":{"FareType":2,"DivideInPartyIndicator":false,"ItinTotalFare":{"BaseFare":86391000.0,"TotalFare":87830850.0,"TotalCommission":0.0,"TotalTax":1439850.0,"ServiceTax":0.0,"Currency":"IRR"},"PtcFareBreakdown":[{"PassengerFare":{"BaseFare":86391000.0,"TotalFare":87830850.0,"Commission":0.0,"ServiceTax":0.0,"Surcharges":[],"Taxes":[{"Amount":1439850.0,"Currency":"IRR","TaxCode":""}],"Currency":"IRR"},"PassengerTypeQuantity":{"PassengerType":1,"Quantity":1},"FareBasisCodes":["YOMTG"]}],"FareInfoes":[]},"OriginDestinationOptions":[{"FlightSegments":[{"DepartureDateTime":"2017-03-08T21:30:00","ArrivalDateTime":"2017-03-09T06:50:00","StopQuantity":0,"FlightNumber":"518","ResBookDesigCode":"Y","JourneyDuration":"06:20","DepartureAirportLocationCode":"DXB","ArrivalAirportLocationCode":"BKK","MarketingAirlineCode":"TG","MarriageGroup":null,"Eticket":true,"CabinClassCode":1,"MealCode":null,"OperatingAirline":{"Code":"TG","FlightNumber":null,"Equipment":"330"},"SeatsRemaining":{"Number":9,"BelowMinimum":true},"IsCharter":false,"IsReturn":false},{"DepartureDateTime":"2017-03-09T21:35:00","ArrivalDateTime":"2017-03-09T23:55:00","StopQuantity":0,"FlightNumber":"325","ResBookDesigCode":"Y","JourneyDuration":"03:50","DepartureAirportLocationCode":"BKK","ArrivalAirportLocationCode":"BLR","MarketingAirlineCode":"TG","MarriageGroup":null,"Eticket":true,"CabinClassCode":1,"MealCode":null,"OperatingAirline":{"Code":"TG","FlightNumber":null,"Equipment":"777"},"SeatsRemaining":{"Number":9,"BelowMinimum":true},"IsCharter":false,"IsReturn":false}]}]},{"IsPassportMandatory":true,"TicketType":"eTicket","DirectionInd":1,"ValidatingAirlineCode":"CX","FareSourceCode":"353337393137263339263232303535","AirItineraryPricingInfo":{"FareType":2,"DivideInPartyIndicator":false,"ItinTotalFare":{"BaseFare":203664300.0,"TotalFare":207983850.0,"TotalCommission":0.0,"TotalTax":4319550.0,"ServiceTax":0.0,"Currency":"IRR"},"PtcFareBreakdown":[{"PassengerFare":{"BaseFare":203664300.0,"TotalFare":207983850.0,"Commission":0.0,"ServiceTax":0.0,"Surcharges":[],"Taxes":[{"Amount":4319550.0,"Currency":"IRR","TaxCode":""}],"Currency":"IRR"},"PassengerTypeQuantity":{"PassengerType":1,"Quantity":1},"FareBasisCodes":["YOW","YOW1"]}],"FareInfoes":[]},"OriginDestinationOptions":[{"FlightSegments":[{"DepartureDateTime":"2017-03-08T00:05:00","ArrivalDateTime":"2017-03-08T11:10:00","StopQuantity":0,"FlightNumber":"738","ResBookDesigCode":"Y","JourneyDuration":"07:05","DepartureAirportLocationCode":"DXB","ArrivalAirportLocationCode":"HKG","MarketingAirlineCode":"CX","MarriageGroup":null,"Eticket":true,"CabinClassCode":1,"MealCode":null,"OperatingAirline":{"Code":"CX","FlightNumber":null,"Equipment":"333"},"SeatsRemaining":{"Number":9,"BelowMinimum":true},"IsCharter":false,"IsReturn":false},{"DepartureDateTime":"2017-03-08T21:00:00","ArrivalDateTime":"2017-03-09T00:30:00","StopQuantity":0,"FlightNumber":"5154","ResBookDesigCode":"Y","JourneyDuration":"06:00","DepartureAirportLocationCode":"HKG","ArrivalAirportLocationCode":"BLR","MarketingAirlineCode":"CX","MarriageGroup":null,"Eticket":true,"CabinClassCode":1,"MealCode":null,"OperatingAirline":{"Code":"KA","FlightNumber":null,"Equipment":"333"},"SeatsRemaining":{"Number":9,"BelowMinimum":true},"IsCharter":false,"IsReturn":false}]}]},{"IsPassportMandatory":true,"TicketType":"eTicket","DirectionInd":1,"ValidatingAirlineCode":"LH","FareSourceCode":"353337393138263339263232303535","AirItineraryPricingInfo":{"FareType":2,"DivideInPartyIndicator":false,"ItinTotalFare":{"BaseFare":200586000.0,"TotalFare":215232750.0,"TotalCommission":0.0,"TotalTax":14646750.0,"ServiceTax":0.0,"Currency":"IRR"},"PtcFareBreakdown":[{"PassengerFare":{"BaseFare":200586000.0,"TotalFare":215232750.0,"Commission":0.0,"ServiceTax":0.0,"Surcharges":[],"Taxes":[{"Amount":14646750.0,"Currency":"IRR","TaxCode":""}],"Currency":"IRR"},"PassengerTypeQuantity":{"PassengerType":1,"Quantity":1},"FareBasisCodes":["G77OW"]}],"FareInfoes":[]},"OriginDestinationOptions":[{"FlightSegments":[{"DepartureDateTime":"2017-03-08T01:50:00","ArrivalDateTime":"2017-03-08T05:45:00","StopQuantity":0,"FlightNumber":"631","ResBookDesigCode":"G","JourneyDuration":"06:55","DepartureAirportLocationCode":"DXB","ArrivalAirportLocationCode":"FRA","MarketingAirlineCode":"LH","MarriageGroup":null,"Eticket":true,"CabinClassCode":2,"MealCode":null,"OperatingAirline":{"Code":"LH","FlightNumber":null,"Equipment":"744"},"SeatsRemaining":{"Number":9,"BelowMinimum":true},"IsCharter":false,"IsReturn":false},{"DepartureDateTime":"2017-03-08T12:50:00","ArrivalDateTime":"2017-03-09T01:50:00","StopQuantity":0,"FlightNumber":"754","ResBookDesigCode":"G","JourneyDuration":"08:30","DepartureAirportLocationCode":"FRA","ArrivalAirportLocationCode":"BLR","MarketingAirlineCode":"LH","MarriageGroup":null,"Eticket":true,"CabinClassCode":2,"MealCode":null,"OperatingAirline":{"Code":"LH","FlightNumber":null,"Equipment":"74H"},"SeatsRemaining":{"Number":9,"BelowMinimum":true},"IsCharter":false,"IsReturn":false}]}]}]}