{"Success":true,"Error":null,"PricedItineraries":[{"IsPassportMandatory":true,"TicketType":null,"DirectionInd":2,"ValidatingAirlineCode":"G9","FareSourceCode":"63653039356462396337313734663530613432356330663439383766393262332634332633333831383939","AirItineraryPricingInfo":{"FareType":4,"DivideInPartyIndicator":false,"ItinTotalFare":{"BaseFare":33242032.0000000000,"TotalFare":34782648.0000000000,"TotalCommission":0.0,"TotalTax":0.0,"ServiceTax":1540616.0000000000,"Currency":"IRR"},"PtcFareBreakdown":[{"PassengerFare":{"BaseFare":33242032.0000000000,"TotalFare":34782648.0000000000,"Commission":0.0,"ServiceTax":1540616.0000000000,"Surcharges":[],"Taxes":[{"Amount":0.0,"Currency":"IRR","TaxCode":""}],"Currency":"IRR"},"PassengerTypeQuantity":{"PassengerType":1,"Quantity":1},"FareBasisCodes":null}],"FareInfoes":[]},"OriginDestinationOptions":[{"FlightSegments":[{"DepartureDateTime":"2017-06-19T03:55:00","ArrivalDateTime":"2017-06-19T06:20:00","StopQuantity":0,"FlightNumber":"426","ResBookDesigCode":null,"JourneyDuration":"03:55","DepartureAirportLocationCode":"COK","ArrivalAirportLocationCode":"SHJ","MarketingAirlineCode":"G9","MarriageGroup":null,"Eticket":true,"CabinClassCode":1,"MealCode":null,"OperatingAirline":{"Code":"G9","FlightNumber":"426","Equipment":""},"SeatsRemaining":null,"IsCharter":false,"IsReturn":false},{"DepartureDateTime":"2017-06-19T11:40:00","ArrivalDateTime":"2017-06-19T14:15:00","StopQuantity":0,"FlightNumber":"205","ResBookDesigCode":null,"JourneyDuration":"02:05","DepartureAirportLocationCode":"SHJ","ArrivalAirportLocationCode":"MHD","MarketingAirlineCode":"G9","MarriageGroup":null,"Eticket":true,"CabinClassCode":1,"MealCode":null,"OperatingAirline":{"Code":"G9","FlightNumber":"205","Equipment":""},"SeatsRemaining":null,"IsCharter":false,"IsReturn":false}]},{"FlightSegments":[{"DepartureDateTime":"2017-06-22T14:55:00","ArrivalDateTime":"2017-06-22T16:35:00","StopQuantity":0,"FlightNumber":"206","ResBookDesigCode":null,"JourneyDuration":"02:10","DepartureAirportLocationCode":"MHD","ArrivalAirportLocationCode":"SHJ","MarketingAirlineCode":"G9","MarriageGroup":null,"Eticket":true,"CabinClassCode":1,"MealCode":null,"OperatingAirline":{"Code":"G9","FlightNumber":"206","Equipment":""},"SeatsRemaining":null,"IsCharter":false,"IsReturn":true},{"DepartureDateTime":"2017-06-22T21:45:00","ArrivalDateTime":"2017-06-23T03:15:00","StopQuantity":0,"FlightNumber":"425","ResBookDesigCode":null,"JourneyDuration":"04:00","DepartureAirportLocationCode":"SHJ","ArrivalAirportLocationCode":"COK","MarketingAirlineCode":"G9","MarriageGroup":null,"Eticket":true,"CabinClassCode":1,"MealCode":null,"OperatingAirline":{"Code":"G9","FlightNumber":"425","Equipment":""},"SeatsRemaining":null,"IsCharter":false,"IsReturn":true}]}]},{"IsPassportMandatory":true,"TicketType":null,"DirectionInd":2,"ValidatingAirlineCode":"WY","FareSourceCode":"643761613234363862303661343937633835666235343766366131353064326126322633333831383939","AirItineraryPricingInfo":{"FareType":2,"DivideInPartyIndicator":false,"ItinTotalFare":{"BaseFare":37942448.0000000000,"TotalFare":41443376.0000000000,"TotalCommission":0.0,"TotalTax":3500928.0000000000,"ServiceTax":0.0,"Currency":"IRR"},"PtcFareBreakdown":[{"PassengerFare":{"BaseFare":37942448.0000000000,"TotalFare":41443376.0000000000,"Commission":0.0,"ServiceTax":0.0,"Surcharges":[],"Taxes":[{"Amount":3500928.0000000000,"Currency":"IRR","TaxCode":""}],"Currency":"IRR"},"PassengerTypeQuantity":{"PassengerType":1,"Quantity":1},"FareBasisCodes":null}],"FareInfoes":[]},"OriginDestinationOptions":[{"FlightSegments":[{"DepartureDateTime":"2017-06-19T09:50:00","ArrivalDateTime":"2017-06-19T12:00:00","StopQuantity":0,"FlightNumber":"226","ResBookDesigCode":"N","JourneyDuration":"03:40","DepartureAirportLocationCode":"COK","ArrivalAirportLocationCode":"MCT","MarketingAirlineCode":"WY","MarriageGroup":null,"Eticket":true,"CabinClassCode":1,"MealCode":null,"OperatingAirline":{"Code":"WY","FlightNumber":"226","Equipment":"738"},"SeatsRemaining":null,"IsCharter":false,"IsReturn":false},{"DepartureDateTime":"2017-06-19T14:00:00","ArrivalDateTime":"2017-06-19T17:00:00","StopQuantity":0,"FlightNumber":"453","ResBookDesigCode":"N","JourneyDuration":"02:30","DepartureAirportLocationCode":"MCT","ArrivalAirportLocationCode":"MHD","MarketingAirlineCode":"WY","MarriageGroup":null,"Eticket":true,"CabinClassCode":1,"MealCode":null,"OperatingAirline":{"Code":"WY","FlightNumber":"453","Equipment":"E75"},"SeatsRemaining":null,"IsCharter":false,"IsReturn":false}]},{"FlightSegments":[{"DepartureDateTime":"2017-06-22T18:00:00","ArrivalDateTime":"2017-06-22T20:15:00","StopQuantity":0,"FlightNumber":"454","ResBookDesigCode":"Y","JourneyDuration":"02:45","DepartureAirportLocationCode":"MHD","ArrivalAirportLocationCode":"MCT","MarketingAirlineCode":"WY","MarriageGroup":null,"Eticket":true,"CabinClassCode":1,"MealCode":null,"OperatingAirline":{"Code":"WY","FlightNumber":"454","Equipment":"E75"},"SeatsRemaining":null,"IsCharter":false,"IsReturn":true},{"DepartureDateTime":"2017-06-23T01:50:00","ArrivalDateTime":"2017-06-23T07:00:00","StopQuantity":0,"FlightNumber":"225","ResBookDesigCode":"Y","JourneyDuration":"03:40","DepartureAirportLocationCode":"MCT","ArrivalAirportLocationCode":"COK","MarketingAirlineCode":"WY","MarriageGroup":null,"Eticket":true,"CabinClassCode":1,"MealCode":null,"OperatingAirline":{"Code":"WY","FlightNumber":"225","Equipment":"738"},"SeatsRemaining":null,"IsCharter":false,"IsReturn":true}]}]},{"IsPassportMandatory":true,"TicketType":null,"DirectionInd":2,"ValidatingAirlineCode":"QR","FareSourceCode":"393837653164303037656534346432336231393934346534363537326334343726322633333831383939","AirItineraryPricingInfo":{"FareType":2,"DivideInPartyIndicator":false,"ItinTotalFare":{"BaseFare":40812080.0000000000,"TotalFare":50245808.0000000000,"TotalCommission":0.0,"TotalTax":9433728.0000000000,"ServiceTax":0.0,"Currency":"IRR"},"PtcFareBreakdown":[{"PassengerFare":{"BaseFare":40812080.0000000000,"TotalFare":50245808.0000000000,"Commission":0.0,"ServiceTax":0.0,"Surcharges":[],"Taxes":[{"Amount":9433728.0000000000,"Currency":"IRR","TaxCode":""}],"Currency":"IRR"},"PassengerTypeQuantity":{"PassengerType":1,"Quantity":1},"FareBasisCodes":null}],"FareInfoes":[]},"OriginDestinationOptions":[{"FlightSegments":[{"DepartureDateTime":"2017-06-19T10:55:00","ArrivalDateTime":"2017-06-19T12:50:00","StopQuantity":0,"FlightNumber":"515","ResBookDesigCode":"N","JourneyDuration":"04:25","DepartureAirportLocationCode":"COK","ArrivalAirportLocationCode":"DOH","MarketingAirlineCode":"QR","MarriageGroup":null,"Eticket":true,"CabinClassCode":1,"MealCode":null,"OperatingAirline":{"Code":"QR","FlightNumber":"515","Equipment":"333"},"SeatsRemaining":null,"IsCharter":false,"IsReturn":false},{"DepartureDateTime":"2017-06-20T00:30:00","ArrivalDateTime":"2017-06-20T04:20:00","StopQuantity":0,"FlightNumber":"494","ResBookDesigCode":"N","JourneyDuration":"02:20","DepartureAirportLocationCode":"DOH","ArrivalAirportLocationCode":"MHD","MarketingAirlineCode":"QR","MarriageGroup":null,"Eticket":true,"CabinClassCode":1,"MealCode":null,"OperatingAirline":{"Code":"QR","FlightNumber":"494","Equipment":"320"},"SeatsRemaining":null,"IsCharter":false,"IsReturn":false}]},{"FlightSegments":[{"DepartureDateTime":"2017-06-22T23:50:00","ArrivalDateTime":"2017-06-23T00:55:00","StopQuantity":0,"FlightNumber":"493","ResBookDesigCode":"Y","JourneyDuration":"02:35","DepartureAirportLocationCode":"MHD","ArrivalAirportLocationCode":"DOH","MarketingAirlineCode":"QR","MarriageGroup":null,"Eticket":true,"CabinClassCode":1,"MealCode":null,"OperatingAirline":{"Code":"QR","FlightNumber":"493","Equipment":"320"},"SeatsRemaining":null,"IsCharter":false,"IsReturn":true},{"DepartureDateTime":"2017-06-23T02:30:00","ArrivalDateTime":"2017-06-23T08:45:00","StopQuantity":0,"FlightNumber":"570","ResBookDesigCode":"Y","JourneyDuration":"03:45","DepartureAirportLocationCode":"DOH","ArrivalAirportLocationCode":"DEL","MarketingAirlineCode":"QR","MarriageGroup":null,"Eticket":true,"CabinClassCode":1,"MealCode":null,"OperatingAirline":{"Code":"QR","FlightNumber":"570","Equipment":"788"},"SeatsRemaining":null,"IsCharter":false,"IsReturn":true},{"DepartureDateTime":"2017-06-23T13:40:00","ArrivalDateTime":"2017-06-23T16:55:00","StopQuantity":0,"FlightNumber":"885","ResBookDesigCode":"N","JourneyDuration":"03:15","DepartureAirportLocationCode":"DEL","ArrivalAirportLocationCode":"COK","MarketingAirlineCode":"UK","MarriageGroup":null,"Eticket":true,"CabinClassCode":1,"MealCode":null,"OperatingAirline":{"Code":"UK","FlightNumber":"885","Equipment":"320"},"SeatsRemaining":null,"IsCharter":false,"IsReturn":true}]}]},{"IsPassportMandatory":true,"TicketType":null,"DirectionInd":2,"ValidatingAirlineCode":"QR","FareSourceCode":"376562353434313362316466343865616233633863666662393331353865333926322633333831383939","AirItineraryPricingInfo":{"FareType":2,"DivideInPartyIndicator":false,"ItinTotalFare":{"BaseFare":46348976.0000000000,"TotalFare":58480688.0000000000,"TotalCommission":0.0,"TotalTax":12131712.0000000000,"ServiceTax":0.0,"Currency":"IRR"},"PtcFareBreakdown":[{"PassengerFare":{"BaseFare":46348976.0000000000,"TotalFare":58480688.0000000000,"Commission":0.0,"ServiceTax":0.0,"Surcharges":[],"Taxes":[{"Amount":12131712.0000000000,"Currency":"IRR","TaxCode":""}],"Currency":"IRR"},"PassengerTypeQuantity":{"PassengerType":1,"Quantity":1},"FareBasisCodes":null}],"FareInfoes":[]},"OriginDestinationOptions":[{"FlightSegments":[{"DepartureDateTime":"2017-06-19T10:55:00","ArrivalDateTime":"2017-06-19T12:50:00","StopQuantity":0,"FlightNumber":"515","ResBookDesigCode":"N","JourneyDuration":"04:25","DepartureAirportLocationCode":"COK","ArrivalAirportLocationCode":"DOH","MarketingAirlineCode":"QR","MarriageGroup":null,"Eticket":true,"CabinClassCode":1,"MealCode":null,"OperatingAirline":{"Code":"QR","FlightNumber":"515","Equipment":"333"},"SeatsRemaining":null,"IsCharter":false,"IsReturn":false},{"DepartureDateTime":"2017-06-20T00:30:00","ArrivalDateTime":"2017-06-20T04:20:00","StopQuantity":0,"FlightNumber":"494","ResBookDesigCode":"N","JourneyDuration":"02:20","DepartureAirportLocationCode":"DOH","ArrivalAirportLocationCode":"MHD","MarketingAirlineCode":"QR","MarriageGroup":null,"Eticket":true,"CabinClassCode":1,"MealCode":null,"OperatingAirline":{"Code":"QR","FlightNumber":"494","Equipment":"320"},"SeatsRemaining":null,"IsCharter":false,"IsReturn":false}]},{"FlightSegments":[{"DepartureDateTime":"2017-06-22T23:50:00","ArrivalDateTime":"2017-06-23T00:55:00","StopQuantity":0,"FlightNumber":"493","ResBookDesigCode":"J","JourneyDuration":"02:35","DepartureAirportLocationCode":"MHD","ArrivalAirportLocationCode":"DOH","MarketingAirlineCode":"QR","MarriageGroup":null,"Eticket":true,"CabinClassCode":3,"MealCode":null,"OperatingAirline":{"Code":"QR","FlightNumber":"493","Equipment":"320"},"SeatsRemaining":null,"IsCharter":false,"IsReturn":true},{"DepartureDateTime":"2017-06-23T02:45:00","ArrivalDateTime":"2017-06-23T09:40:00","StopQuantity":0,"FlightNumber":"514","ResBookDesigCode":"J","JourneyDuration":"04:25","DepartureAirportLocationCode":"DOH","ArrivalAirportLocationCode":"COK","MarketingAirlineCode":"QR","MarriageGroup":null,"Eticket":true,"CabinClassCode":3,"MealCode":null,"OperatingAirline":{"Code":"QR","FlightNumber":"514","Equipment":"333"},"SeatsRemaining":null,"IsCharter":false,"IsReturn":true}]}]},{"IsPassportMandatory":true,"TicketType":null,"DirectionInd":2,"ValidatingAirlineCode":"GF","FareSourceCode":"37623334326531386466366434313437393762643436633261346437393537342635302633333831383939","AirItineraryPricingInfo":{"FareType":2,"DivideInPartyIndicator":false,"ItinTotalFare":{"BaseFare":55672800.00000000000,"TotalFare":64051680.00000000000,"TotalCommission":0.0,"TotalTax":8378880.0000000000,"ServiceTax":0.0,"Currency":"IRR"},"PtcFareBreakdown":[{"PassengerFare":{"BaseFare":55672800.00000000000,"TotalFare":64051680.00000000000,"Commission":0.0,"ServiceTax":0.0,"Surcharges":[],"Taxes":[{"Amount":8378880.0000000000,"Currency":"IRR","TaxCode":""}],"Currency":"IRR"},"PassengerTypeQuantity":{"PassengerType":1,"Quantity":1},"FareBasisCodes":null}],"FareInfoes":[]},"OriginDestinationOptions":[{"FlightSegments":[{"DepartureDateTime":"2017-06-19T04:35:00","ArrivalDateTime":"2017-06-19T06:45:00","StopQuantity":0,"FlightNumber":"271","ResBookDesigCode":"N","JourneyDuration":"04:40","DepartureAirportLocationCode":"COK","ArrivalAirportLocationCode":"BAH","MarketingAirlineCode":"GF","MarriageGroup":null,"Eticket":true,"CabinClassCode":1,"MealCode":null,"OperatingAirline":{"Code":"GF","FlightNumber":"271","Equipment":"321"},"SeatsRemaining":null,"IsCharter":false,"IsReturn":false},{"DepartureDateTime":"2017-06-19T08:15:00","ArrivalDateTime":"2017-06-19T10:25:00","StopQuantity":0,"FlightNumber":"24","ResBookDesigCode":"R","JourneyDuration":"01:10","DepartureAirportLocationCode":"BAH","ArrivalAirportLocationCode":"DXB","MarketingAirlineCode":"FZ","MarriageGroup":null,"Eticket":true,"CabinClassCode":1,"MealCode":null,"OperatingAirline":{"Code":"FZ","FlightNumber":"24","Equipment":"73H"},"SeatsRemaining":null,"IsCharter":false,"IsReturn":false},{"DepartureDateTime":"2017-06-19T12:00:00","ArrivalDateTime":"2017-06-19T14:45:00","StopQuantity":0,"FlightNumber":"251","ResBookDesigCode":"R","JourneyDuration":"02:15","DepartureAirportLocationCode":"DXB","ArrivalAirportLocationCode":"MHD","MarketingAirlineCode":"FZ","MarriageGroup":null,"Eticket":true,"CabinClassCode":1,"MealCode":null,"OperatingAirline":{"Code":"FZ","FlightNumber":"251","Equipment":"73H"},"SeatsRemaining":null,"IsCharter":false,"IsReturn":false}]},{"FlightSegments":[{"DepartureDateTime":"2017-06-22T15:45:00","ArrivalDateTime":"2017-06-22T17:40:00","StopQuantity":0,"FlightNumber":"252","ResBookDesigCode":"I","JourneyDuration":"02:25","DepartureAirportLocationCode":"MHD","ArrivalAirportLocationCode":"DXB","MarketingAirlineCode":"FZ","MarriageGroup":null,"Eticket":true,"CabinClassCode":1,"MealCode":null,"OperatingAirline":{"Code":"FZ","FlightNumber":"252","Equipment":"73H"},"SeatsRemaining":null,"IsCharter":false,"IsReturn":true},{"DepartureDateTime":"2017-06-23T03:05:00","ArrivalDateTime":"2017-06-23T08:40:00","StopQuantity":0,"FlightNumber":"9011","ResBookDesigCode":"M","JourneyDuration":"04:05","DepartureAirportLocationCode":"DXB","ArrivalAirportLocationCode":"COK","MarketingAirlineCode":"H1","MarriageGroup":null,"Eticket":true,"CabinClassCode":1,"MealCode":null,"OperatingAirline":{"Code":"SG","FlightNumber":"9011","Equipment":"737"},"SeatsRemaining":null,"IsCharter":false,"IsReturn":true}]}]}]}